Workbook

Sheet Financials>

Sheet Historical FS
B2: ="Historical Financial Statements - "&'Data Sheet'!B1 -> Historical Financial Statements - MARUTI SUZUKI INDIA LTD
B4: Years | C4: ='Data Sheet'!B16 -> 42825 | D4: ='Data Sheet'!C16 -> 43190 | E4: ='Data Sheet'!D16 -> 43555 | F4: ='Data Sheet'!E16 -> 43921 | G4: ='Data Sheet'!F16 -> 44286 | H4: ='Data Sheet'!G16 -> 44651 | I4: ='Data Sheet'!H16 -> 45016 | J4: ='Data Sheet'!I16 -> 45382 | ... L4: ='Data Sheet'!K16 -> 46112 | M4: LTM
A6: # | B6: Income Statement
B7: Sales | C7: =IFERROR('Data Sheet'!B17,0) -> 68085 | D7: =IFERROR('Data Sheet'!C17,0) -> 79809.4 | E7: =IFERROR('Data Sheet'!D17,0) -> 86068.5 | F7: =IFERROR('Data Sheet'!E17,0) -> 75660 | G7: =IFERROR('Data Sheet'!F17,0) -> 70372 | H7: =IFERROR('Data Sheet'!G17,0) -> 88329.8 | I7: =IFERROR('Data Sheet'!H17,0) -> 117571.3 | J7: =IFERROR('Data Sheet'!I17,0) -> 141858.2 | ... L7: =IFERROR('Data Sheet'!K17,0) -> 183316 | M7: =IFERROR(SUM('Data Sheet'!H42:K42),0) -> 183316
B8: Sales Growth | C8: 0 | D8: =D7/C7-1 -> 0.17220239 | E8: =E7/D7-1 -> 0.078425599 | F8: =F7/E7-1 -> -0.12093275 | G8: =G7/F7-1 -> -0.06989162 | H8: =H7/G7-1 -> 0.25518388 | I8: =I7/H7-1 -> 0.33104909 | J8: =J7/I7-1 -> 0.20657167 | K8: =K7/J7-1 -> 0.077928523 | ... M8: =M7/L7-1 -> 0
B10: COGS | C10: =IFERROR('Data Sheet'!B20,0) -> 518.6 | D10: =IFERROR('Data Sheet'!C20,0) -> 673.4 | E10: =IFERROR('Data Sheet'!D20,0) -> 863.3 | F10: =IFERROR('Data Sheet'!E20,0) -> 699.5 | G10: =IFERROR('Data Sheet'!F20,0) -> 476.6 | H10: =IFERROR('Data Sheet'!G20,0) -> 630.9 | I10: =IFERROR('Data Sheet'!H20,0) -> 790 | J10: =IFERROR('Data Sheet'!I20,0) -> 1033.4 | ... M10: =IFERROR('Data Sheet'!L20,0) -> 0
B11: COGS % Sales | C11: =C10/C7 -> 0.0076169494 | D11: =D10/D7 -> 0.0084376026 | E11: =E10/E7 -> 0.010030383 | F11: =F10/F7 -> 0.009245308 | G11: =G10/G7 -> 0.00677258 | H11: =H10/H7 -> 0.0071425499 | I11: =I10/I7 -> 0.0067193269 | J11: =J10/J7 -> 0.0072847393 | ... M11: =M10/M7 -> 0
B13: Gross Profit | C13: =C7-C10 -> 67566.4 | D13: =D7-D10 -> 79136 | E13: =E7-E10 -> 85205.2 | F13: =F7-F10 -> 74960.5 | G13: =G7-G10 -> 69895.4 | H13: =H7-H10 -> 87698.9 | I13: =I7-I10 -> 116781.3 | J13: =J7-J10 -> 140824.8 | ... M13: =M7-M10 -> 183316
B14: Gross Margins | C14: =C13/C7 -> 0.99238305 | D14: =D13/D7 -> 0.9915624 | E14: =E13/E7 -> 0.98996962 | F14: =F13/F7 -> 0.99075469 | G14: =G13/G7 -> 0.99322742 | H14: =H13/H7 -> 0.99285745 | I14: =I13/I7 -> 0.99328067 | J14: =J13/J7 -> 0.99271526 | ... M14: =M13/M7 -> 1
B16: Selling & General Expenses | C16: =IFERROR(SUM('Data Sheet'!B23,'Data Sheet'!B24),0) -> 7659.7 | D16: =IFERROR(SUM('Data Sheet'!C23,'Data Sheet'!C24),0) -> 8706.5 | E16: =IFERROR(SUM('Data Sheet'!D23,'Data Sheet'!D24),0) -> 10830 | F16: =IFERROR(SUM('Data Sheet'!E23,'Data Sheet'!E24),0) -> 10647.9 | G16: =IFERROR(SUM('Data Sheet'!F23,'Data Sheet'!F24),0) -> 9545.8 | H16: =IFERROR(SUM('Data Sheet'!G23,'Data Sheet'!G24),0) -> 10999 | I16: =IFERROR(SUM('Data Sheet'!H23,'Data Sheet'!H24),0) -> 13746 | J16: =IFERROR(SUM('Data Sheet'!I23,'Data Sheet'!I24),0) -> 15216.7 | ... M16: =IFERROR(SUM('Data Sheet'!L23,'Data Sheet'!L24),0) -> 0
B17: S&G % Sales | C17: =C16/C7 -> 0.11250202 | D17: =D16/D7 -> 0.10909116 | E17: =E16/E7 -> 0.12583001 | F17: =F16/F7 -> 0.14073354 | G17: =G16/G7 -> 0.1356477 | H17: =H16/H7 -> 0.12452196 | I17: =I16/I7 -> 0.11691629 | J17: =J16/J7 -> 0.10726698 | ... M17: =M16/M7 -> 0
B19: EBITDA | C19: =C13-C16 -> 59906.7 | D19: =D13-D16 -> 70429.5 | E19: =E13-E16 -> 74375.2 | F19: =F13-F16 -> 64312.6 | G19: =G13-G16 -> 60349.6 | H19: =H13-H16 -> 76699.9 | I19: =I13-I16 -> 103035.3 | J19: =J13-J16 -> 125608.1 | ... M19: =M13-M16 -> 183316
B20: EBITDA Margains | C20: =C19/C7 -> 0.87988103 | D20: =D19/D7 -> 0.88247124 | E20: =E19/E7 -> 0.86413961 | F20: =F19/F7 -> 0.85002115 | G20: =G19/G7 -> 0.85757972 | H20: =H19/H7 -> 0.86833549 | I20: =I19/I7 -> 0.87636438 | J20: =J19/J7 -> 0.88544829 | ... M20: =M19/M7 -> 1
B22: Interest | C22: =IFERROR('Data Sheet'!B27, 0) -> 89.4 | D22: =IFERROR('Data Sheet'!C27, 0) -> 345.8 | E22: =IFERROR('Data Sheet'!D27, 0) -> 75.9 | F22: =IFERROR('Data Sheet'!E27, 0) -> 134.2 | G22: =IFERROR('Data Sheet'!F27, 0) -> 101.8 | H22: =IFERROR('Data Sheet'!G27, 0) -> 126.6 | I22: =IFERROR('Data Sheet'!H27, 0) -> 187 | J22: =IFERROR('Data Sheet'!I27, 0) -> 193.6 | ... L22: =IFERROR('Data Sheet'!K27, 0) -> 238.7 | M22: =IFERROR(SUM('Data Sheet'!H27:K27),0) -> 813.5
B23: Interest % Sales | C23: =C22/C7 -> 0.0013130646 | D23: =D22/D7 -> 0.004332823 | E23: =E22/E7 -> 0.00088185573 | F23: =F22/F7 -> 0.0017737246 | G23: =G22/G7 -> 0.0014465981 | H23: =H22/H7 -> 0.0014332649 | I23: =I22/I7 -> 0.0015905242 | J23: =J22/J7 -> 0.0013647431 | ... M23: =M22/M7 -> 0.0044376923
B25: Depreciation | C25: =IFERROR('Data Sheet'!B26,0) -> 2603.9 | D25: =IFERROR('Data Sheet'!C26,0) -> 2759.8 | E25: =IFERROR('Data Sheet'!D26,0) -> 3020.8 | F25: =IFERROR('Data Sheet'!E26,0) -> 3528.4 | G25: =IFERROR('Data Sheet'!F26,0) -> 3034.1 | H25: =IFERROR('Data Sheet'!G26,0) -> 2789 | I25: =IFERROR('Data Sheet'!H26,0) -> 2825.7 | J25: =IFERROR('Data Sheet'!I26,0) -> 5255.8 | ... L25: =IFERROR('Data Sheet'!K26,0) -> 6741.7 | M25: =IFERROR(SUM('Data Sheet'!H26:K26),0) -> 20431.4
B26: Depreciation % Sales | C26: =C25/C7 -> 0.038244841 | D26: =D25/D7 -> 0.034579887 | E26: =E25/E7 -> 0.035097626 | F26: =F25/F7 -> 0.046634946 | G26: =G25/G7 -> 0.043115159 | H26: =H25/H7 -> 0.031574848 | I26: =I25/I7 -> 0.024033927 | J26: =J25/J7 -> 0.037049674 | ... M26: =M25/M7 -> 0.11145454
B28: Earnings Before Tax (EBT) | C28: =IFERROR(C19-SUM(C25,C22),0) -> 57213.4 | D28: =IFERROR(D19-SUM(D25,D22),0) -> 67323.9 | E28: =IFERROR(E19-SUM(E25,E22),0) -> 71278.5 | F28: =IFERROR(F19-SUM(F25,F22),0) -> 60650 | G28: =IFERROR(G19-SUM(G25,G22),0) -> 57213.7 | H28: =IFERROR(H19-SUM(H25,H22),0) -> 73784.3 | I28: =IFERROR(I19-SUM(I25,I22),0) -> 100022.6 | J28: =IFERROR(J19-SUM(J25,J22),0) -> 120158.7 | ... M28: =IFERROR(M19-SUM(M25,M22),0) -> 162071.1
B29: EBT % Sales | C29: =C28/C7 -> 0.84032313 | D29: =D28/D7 -> 0.84355853 | E29: =E28/E7 -> 0.82816013 | F29: =F28/F7 -> 0.80161248 | G29: =G28/G7 -> 0.81301796 | H29: =H28/H7 -> 0.83532738 | I29: =I28/I7 -> 0.85073993 | J29: =J28/J7 -> 0.84703387 | ... M29: =M28/M7 -> 0.88410777
B31: Tax | C31: =IFERROR('Data Sheet'!B29,0) -> 2616.2 | D31: =IFERROR('Data Sheet'!C29,0) -> 3286.2 | E31: =IFERROR('Data Sheet'!D29,0) -> 2973.2 | F31: =IFERROR('Data Sheet'!E29,0) -> 1425.2 | G31: =IFERROR('Data Sheet'!F29,0) -> 931.9 | H31: =IFERROR('Data Sheet'!G29,0) -> 817.7 | I31: =IFERROR('Data Sheet'!H29,0) -> 2112.1 | J31: =IFERROR('Data Sheet'!I29,0) -> 3936.3 | ... L31: =IFERROR('Data Sheet'!K29,0) -> 4439 | M31: =IFERROR(SUM('Data Sheet'!H48:K48),0) -> 4439
B32: Effective Tax Rate | C32: =C31/C28 -> 0.04572705 | D32: =D31/D28 -> 0.048811789 | E32: =E31/E28 -> 0.041712438 | F32: =F31/F28 -> 0.023498763 | G32: =G31/G28 -> 0.016288057 | H32: =H31/H28 -> 0.011082303 | I32: =I31/I28 -> 0.021116228 | J32: =J31/J28 -> 0.032759176 | ... M32: =M31/M28 -> 0.027389214
B34: Net Profit | C34: =IFERROR(C28-C31,0) -> 54597.2 | D34: =IFERROR(D28-D31,0) -> 64037.7 | E34: =IFERROR(E28-E31,0) -> 68305.3 | F34: =IFERROR(F28-F31,0) -> 59224.8 | G34: =IFERROR(G28-G31,0) -> 56281.8 | H34: =IFERROR(H28-H31,0) -> 72966.6 | I34: =IFERROR(I28-I31,0) -> 97910.5 | J34: =IFERROR(J28-J31,0) -> 116222.4 | ... M34: =IFERROR(M28-M31,0) -> 157632.1
B35: Net Margins % | C35: =C34/C7 -> 0.80189763 | D35: =D34/D7 -> 0.80238293 | E35: =E34/E7 -> 0.79361555 | F35: =F34/F7 -> 0.78277557 | G35: =G34/G7 -> 0.79977548 | H35: =H34/H7 -> 0.82607002 | I35: =I34/I7 -> 0.83277552 | J35: =J34/J7 -> 0.81928574 | ... M35: =M34/M7 -> 0.85989275
B37: No. of Equity Shares | C37: =IFERROR('Data Sheet'!B93, 0) -> 30.21 | D37: =IFERROR('Data Sheet'!C93, 0) -> 30.21 | E37: =IFERROR('Data Sheet'!D93, 0) -> 30.21 | F37: =IFERROR('Data Sheet'!E93, 0) -> 30.21 | G37: =IFERROR('Data Sheet'!F93, 0) -> 30.21 | H37: =IFERROR('Data Sheet'!G93, 0) -> 30.21 | I37: =IFERROR('Data Sheet'!H93, 0) -> 30.21 | J37: =IFERROR('Data Sheet'!I93, 0) -> 31.44 | ... M37: =IFERROR('Data Sheet'!L93, 0) -> 0
B39: EPS | C39: =IFERROR(C34/C37,0) -> 1807.2559 | D39: =IFERROR(D34/D37,0) -> 2119.7517 | E39: =IFERROR(E34/E37,0) -> 2261.0162 | F39: =IFERROR(F34/F37,0) -> 1960.4369 | G39: =IFERROR(G34/G37,0) -> 1863.0189 | H39: =IFERROR(H34/H37,0) -> 2415.3128 | I39: =IFERROR(I34/I37,0) -> 3240.9964 | J39: =IFERROR(J34/J37,0) -> 3696.6412 | ... M39: =IFERROR(M34/M37,0) -> 0
B40: EPS Growth % | D40: =IFERROR(D39/C39-1,0) -> 0.1729118 | E40: =IFERROR(E39/D39-1,0) -> 0.066641994 | F40: =IFERROR(F39/E39-1,0) -> -0.1329399 | G40: =IFERROR(G39/F39-1,0) -> -0.049692021 | H40: =IFERROR(H39/G39-1,0) -> 0.29645107 | I40: =IFERROR(I39/H39-1,0) -> 0.34185367 | J40: =IFERROR(J39/I39-1,0) -> 0.1405879 | K40: =IFERROR(K39/J39-1,0) -> 0.082515935 | ... M40: =IFERROR(M39/L39-1,0) -> -1
B42: Dividend per share | C42: =IFERROR('Data Sheet'!B31/'Historical FS'!C37, 0) -> 74.975174 | D42: =IFERROR('Data Sheet'!C31/'Historical FS'!D37, 0) -> 79.973519 | E42: =IFERROR('Data Sheet'!D31/'Historical FS'!E37, 0) -> 79.973519 | F42: =IFERROR('Data Sheet'!E31/'Historical FS'!F37, 0) -> 59.980139 | G42: =IFERROR('Data Sheet'!F31/'Historical FS'!G37, 0) -> 44.985104 | H42: =IFERROR('Data Sheet'!G31/'Historical FS'!H37, 0) -> 59.980139 | I42: =IFERROR('Data Sheet'!H31/'Historical FS'!I37, 0) -> 89.970209 | J42: =IFERROR('Data Sheet'!I31/'Historical FS'!J37, 0) -> 125 | ... M42: =IFERROR('Data Sheet'!L31/'Historical FS'!M37, 0) -> 0
B43: Dividend payout ratio | C43: =IFERROR(C42/C39,0) -> 0.041485644 | D43: =IFERROR(D42/D39,0) -> 0.037727776 | E43: =IFERROR(E42/E39,0) -> 0.035370608 | F43: =IFERROR(F42/F39,0) -> 0.030595291 | G43: =IFERROR(G42/G39,0) -> 0.024146349 | H43: =IFERROR(H42/H39,0) -> 0.02483328 | I43: =IFERROR(I42/I39,0) -> 0.027760046 | J43: =IFERROR(J42/J39,0) -> 0.03381448 | ... M43: =IFERROR(M42/M39,0) -> 0
B45: Retained Earnings | C45: =IFERROR(1-C43,0) -> 0.95851436 | D45: =IFERROR(1-D43,0) -> 0.96227222 | E45: =IFERROR(1-E43,0) -> 0.96462939 | F45: =IFERROR(1-F43,0) -> 0.96940471 | G45: =IFERROR(1-G43,0) -> 0.97585365 | H45: =IFERROR(1-H43,0) -> 0.97516672 | I45: =IFERROR(1-I43,0) -> 0.97223995 | J45: =IFERROR(1-J43,0) -> 0.96618552 | ... M45: =IFERROR(1-M43,0) -> 1
A49: # | B49: Balance Sheet
B50: Equity Share Capital | C50: =IFERROR('Data Sheet'!B57, 0) -> 151 | D50: =IFERROR('Data Sheet'!C57, 0) -> 151 | E50: =IFERROR('Data Sheet'!D57, 0) -> 151 | F50: =IFERROR('Data Sheet'!E57, 0) -> 151 | G50: =IFERROR('Data Sheet'!F57, 0) -> 151 | H50: =IFERROR('Data Sheet'!G57, 0) -> 151 | I50: =IFERROR('Data Sheet'!H57, 0) -> 151 | J50: =IFERROR('Data Sheet'!I57, 0) -> 157.2 | ... L50: =IFERROR('Data Sheet'!K57, 0) -> 157.2
B51: Reserves | C51: =IFERROR('Data Sheet'!B58, 0) -> 36924.1 | D51: =IFERROR('Data Sheet'!C58, 0) -> 42408.4 | E51: =IFERROR('Data Sheet'!D58, 0) -> 46941.1 | F51: =IFERROR('Data Sheet'!E58, 0) -> 49262 | G51: =IFERROR('Data Sheet'!F58, 0) -> 52349.6 | H51: =IFERROR('Data Sheet'!G58, 0) -> 55182.5 | I51: =IFERROR('Data Sheet'!H58, 0) -> 61640.3 | J51: =IFERROR('Data Sheet'!I58, 0) -> 85478.8 | ... L51: =IFERROR('Data Sheet'!K58, 0) -> 106999.1
B52: Borrowings | C52: =IFERROR('Data Sheet'!B59, 0) -> 483.6 | D52: =IFERROR('Data Sheet'!C59, 0) -> 120.8 | E52: =IFERROR('Data Sheet'!D59, 0) -> 159.6 | F52: =IFERROR('Data Sheet'!E59, 0) -> 184.1 | G52: =IFERROR('Data Sheet'!F59, 0) -> 540.9 | H52: =IFERROR('Data Sheet'!G59, 0) -> 425.5 | I52: =IFERROR('Data Sheet'!H59, 0) -> 1247.3 | J52: =IFERROR('Data Sheet'!I59, 0) -> 118.6 | ... L52: =IFERROR('Data Sheet'!K59, 0) -> 102.5
B53: Other Liabilities | C53: =IFERROR('Data Sheet'!B60, 0) -> 14401.8 | D53: =IFERROR('Data Sheet'!C60, 0) -> 17568.2 | E53: =IFERROR('Data Sheet'!D60, 0) -> 16717 | F53: =IFERROR('Data Sheet'!E60, 0) -> 14030.6 | G53: =IFERROR('Data Sheet'!F60, 0) -> 18334.6 | H53: =IFERROR('Data Sheet'!G60, 0) -> 18896.5 | I53: =IFERROR('Data Sheet'!H60, 0) -> 21558.3 | J53: =IFERROR('Data Sheet'!I60, 0) -> 29549.5 | ... L53: =IFERROR('Data Sheet'!K60, 0) -> 41622.2
B54: Total Liabilities | C54: =IFERROR('Data Sheet'!B61, 0) -> 51960.5 | D54: =IFERROR('Data Sheet'!C61, 0) -> 60248.4 | E54: =IFERROR('Data Sheet'!D61, 0) -> 63968.7 | F54: =IFERROR('Data Sheet'!E61, 0) -> 63627.7 | G54: =IFERROR('Data Sheet'!F61, 0) -> 71376.1 | H54: =IFERROR('Data Sheet'!G61, 0) -> 74655.5 | I54: =IFERROR('Data Sheet'!H61, 0) -> 84596.9 | J54: =IFERROR('Data Sheet'!I61, 0) -> 115304.1 | ... L54: =IFERROR('Data Sheet'!K61, 0) -> 148881
B56: Fixed Assets Net Block | C56: =IFERROR('Data Sheet'!B62, 0) -> 13310.7 | D56: =IFERROR('Data Sheet'!C62, 0) -> 13388.8 | E56: =IFERROR('Data Sheet'!D62, 0) -> 15437.3 | F56: =IFERROR('Data Sheet'!E62, 0) -> 15744.4 | G56: =IFERROR('Data Sheet'!F62, 0) -> 14988.7 | H56: =IFERROR('Data Sheet'!G62, 0) -> 13747.2 | I56: =IFERROR('Data Sheet'!H62, 0) -> 17830.4 | J56: =IFERROR('Data Sheet'!I62, 0) -> 27864.8 | ... L56: =IFERROR('Data Sheet'!K62, 0) -> 34955.4
B57: Capital Work in Progress | C57: =IFERROR('Data Sheet'!B63, 0) -> 1252.3 | D57: =IFERROR('Data Sheet'!C63, 0) -> 2132.1 | E57: =IFERROR('Data Sheet'!D63, 0) -> 1606.9 | F57: =IFERROR('Data Sheet'!E63, 0) -> 1415.2 | G57: =IFERROR('Data Sheet'!F63, 0) -> 1496.8 | H57: =IFERROR('Data Sheet'!G63, 0) -> 2936.5 | I57: =IFERROR('Data Sheet'!H63, 0) -> 2904.1 | J57: =IFERROR('Data Sheet'!I63, 0) -> 7734.8 | ... L57: =IFERROR('Data Sheet'!K63, 0) -> 9406.2
B58: Investments | C58: =IFERROR('Data Sheet'!B64, 0) -> 29150.6 | D58: =IFERROR('Data Sheet'!C64, 0) -> 36123.1 | E58: =IFERROR('Data Sheet'!D64, 0) -> 37503.6 | F58: =IFERROR('Data Sheet'!E64, 0) -> 37488 | G58: =IFERROR('Data Sheet'!F64, 0) -> 42944.8 | H58: =IFERROR('Data Sheet'!G64, 0) -> 42034.7 | I58: =IFERROR('Data Sheet'!H64, 0) -> 49184.3 | J58: =IFERROR('Data Sheet'!I64, 0) -> 57296 | ... L58: =IFERROR('Data Sheet'!K64, 0) -> 76838.5
B59: Other Assets | C59: =IFERROR('Data Sheet'!B65-SUM('Data Sheet'!B67,'Data Sheet'!B68,'Data Sheet'!B69),0) -> 3757.1 | D59: =IFERROR('Data Sheet'!C65-SUM('Data Sheet'!C67,'Data Sheet'!C68,'Data Sheet'!C69),0) -> 3904.8 | E59: =IFERROR('Data Sheet'!D65-SUM('Data Sheet'!D67,'Data Sheet'!D68,'Data Sheet'!D69),0) -> 3597.7 | F59: =IFERROR('Data Sheet'!E65-SUM('Data Sheet'!E67,'Data Sheet'!E68,'Data Sheet'!E69),0) -> 3759.5 | G59: =IFERROR('Data Sheet'!F65-SUM('Data Sheet'!F67,'Data Sheet'!F68,'Data Sheet'!F69),0) -> 4569.8 | H59: =IFERROR('Data Sheet'!G65-SUM('Data Sheet'!G67,'Data Sheet'!G68,'Data Sheet'!G69),0) -> 7328.1 | I59: =IFERROR('Data Sheet'!H65-SUM('Data Sheet'!H67,'Data Sheet'!H68,'Data Sheet'!H69),0) -> 7051.6 | J59: =IFERROR('Data Sheet'!I65-SUM('Data Sheet'!I67,'Data Sheet'!I68,'Data Sheet'!I69),0) -> 9666.2 | ... L59: =IFERROR('Data Sheet'!K65-SUM('Data Sheet'!K67,'Data Sheet'!K68,'Data Sheet'!K69),0) -> 9438.3
B60: Total Non Current Assets | C60: =IFERROR(SUM(C56,C57,C58,C59),0) -> 47470.7 | D60: =IFERROR(SUM(D56,D57,D58,D59),0) -> 55548.8 | E60: =IFERROR(SUM(E56,E57,E58,E59),0) -> 58145.5 | F60: =IFERROR(SUM(F56,F57,F58,F59),0) -> 58407.1 | G60: =IFERROR(SUM(G56,G57,G58,G59),0) -> 64000.1 | H60: =IFERROR(SUM(H56,H57,H58,H59),0) -> 66046.5 | I60: =IFERROR(SUM(I56,I57,I58,I59),0) -> 76970.4 | J60: =IFERROR(SUM(J56,J57,J58,J59),0) -> 102561.8 | ... L60: =IFERROR(SUM(L56,L57,L58,L59),0) -> 130638.4
B62: Receivables | C62: =IFERROR('Data Sheet'!B67, 0) -> 1202.6 | D62: =IFERROR('Data Sheet'!C67, 0) -> 1465.4 | E62: =IFERROR('Data Sheet'!D67, 0) -> 2312.8 | F62: =IFERROR('Data Sheet'!E67, 0) -> 1977.7 | G62: =IFERROR('Data Sheet'!F67, 0) -> 1279.9 | H62: =IFERROR('Data Sheet'!G67, 0) -> 2034.5 | I62: =IFERROR('Data Sheet'!H67, 0) -> 3301.4 | J62: =IFERROR('Data Sheet'!I67, 0) -> 4596.8 | ... L62: =IFERROR('Data Sheet'!K67, 0) -> 5342
B63: Inventory | C63: =IFERROR('Data Sheet'!B68, 0) -> 3263.7 | D63: =IFERROR('Data Sheet'!C68, 0) -> 3160.2 | E63: =IFERROR('Data Sheet'!D68, 0) -> 3322.6 | F63: =IFERROR('Data Sheet'!E68, 0) -> 3213.9 | G63: =IFERROR('Data Sheet'!F68, 0) -> 3049 | H63: =IFERROR('Data Sheet'!G68, 0) -> 3532.3 | I63: =IFERROR('Data Sheet'!H68, 0) -> 4283.5 | J63: =IFERROR('Data Sheet'!I68, 0) -> 5318.1 | ... L63: =IFERROR('Data Sheet'!K68, 0) -> 11320.6
B64: Cash & Bank | C64: =IFERROR('Data Sheet'!B69, 0) -> 23.5 | D64: =IFERROR('Data Sheet'!C69, 0) -> 74 | E64: =IFERROR('Data Sheet'!D69, 0) -> 187.8 | F64: =IFERROR('Data Sheet'!E69, 0) -> 29 | G64: =IFERROR('Data Sheet'!F69, 0) -> 3047.1 | H64: =IFERROR('Data Sheet'!G69, 0) -> 3042.2 | I64: =IFERROR('Data Sheet'!H69, 0) -> 41.6 | J64: =IFERROR('Data Sheet'!I69, 0) -> 2827.4 | ... L64: =IFERROR('Data Sheet'!K69, 0) -> 1580
B65: Total Current Assets | C65: =SUM(C62,C63,C64) -> 4489.8 | D65: =SUM(D62,D63,D64) -> 4699.6 | E65: =SUM(E62,E63,E64) -> 5823.2 | F65: =SUM(F62,F63,F64) -> 5220.6 | G65: =SUM(G62,G63,G64) -> 7376 | H65: =SUM(H62,H63,H64) -> 8609 | I65: =SUM(I62,I63,I64) -> 7626.5 | J65: =SUM(J62,J63,J64) -> 12742.3 | ... L65: =SUM(L62,L63,L64) -> 18242.6
B67: Total Assets | C67: =SUM(C60+C65) -> 51960.5 | D67: =SUM(D60+D65) -> 60248.4 | E67: =SUM(E60+E65) -> 63968.7 | F67: =SUM(F60+F65) -> 63627.7 | G67: =SUM(G60+G65) -> 71376.1 | H67: =SUM(H60+H65) -> 74655.5 | I67: =SUM(I60+I65) -> 84596.9 | J67: =SUM(J60+J65) -> 115304.1 | ... L67: =SUM(L60+L65) -> 148881
B69: Check | C69: =C67=C54 -> TRUE | D69: =D67=D54 -> TRUE | E69: =E67=E54 -> TRUE | F69: =F67=F54 -> TRUE | G69: =G67=G54 -> TRUE | H69: =H67=H54 -> TRUE | I69: =I67=I54 -> TRUE | J69: =J67=J54 -> TRUE | ... L69: =L67=L54 -> TRUE
A72: # | B72: Cash Flow Statements
B73: Operating Activities
B74: Profit from operations | C74: =IFERROR('Cash Flow'!E5, 0) -> 10413 | D74: =IFERROR('Cash Flow'!F5, 0) -> 12036 | E74: =IFERROR('Cash Flow'!G5, 0) -> 11060 | F74: =IFERROR('Cash Flow'!H5, 0) -> 7503 | G74: =IFERROR('Cash Flow'!I5, 0) -> 5531 | H74: =IFERROR('Cash Flow'!J5, 0) -> 5832 | I74: =IFERROR('Cash Flow'!K5, 0) -> 11112 | J74: =IFERROR('Cash Flow'!L5, 0) -> 18676 | ... L74: =IFERROR('Cash Flow'!N5, 0) -> 21802
B75: Receivables | C75: =IFERROR('Cash Flow'!E6, 0) -> 122 | D75: =IFERROR('Cash Flow'!F6, 0) -> -262 | E75: =IFERROR('Cash Flow'!G6, 0) -> -851 | F75: =IFERROR('Cash Flow'!H6, 0) -> 340 | G75: =IFERROR('Cash Flow'!I6, 0) -> 696 | H75: =IFERROR('Cash Flow'!J6, 0) -> -764 | I75: =IFERROR('Cash Flow'!K6, 0) -> -1258 | J75: =IFERROR('Cash Flow'!L6, 0) -> -1316 | ... L75: =IFERROR('Cash Flow'!N6, 0) -> 1236
B76: Inventory | C76: =IFERROR('Cash Flow'!E7, 0) -> -131 | D76: =IFERROR('Cash Flow'!F7, 0) -> 104 | E76: =IFERROR('Cash Flow'!G7, 0) -> -162 | F76: =IFERROR('Cash Flow'!H7, 0) -> 109 | G76: =IFERROR('Cash Flow'!I7, 0) -> 165 | H76: =IFERROR('Cash Flow'!J7, 0) -> -483 | I76: =IFERROR('Cash Flow'!K7, 0) -> -751 | J76: =IFERROR('Cash Flow'!L7, 0) -> 125 | ... L76: =IFERROR('Cash Flow'!N7, 0) -> -4407
B77: Payables | C77: =IFERROR('Cash Flow'!E8, 0) -> 979 | D77: =IFERROR('Cash Flow'!F8, 0) -> 2128 | E77: =IFERROR('Cash Flow'!G8, 0) -> -858 | F77: =IFERROR('Cash Flow'!H8, 0) -> -2155 | G77: =IFERROR('Cash Flow'!I8, 0) -> 2680 | H77: =IFERROR('Cash Flow'!J8, 0) -> -396 | I77: =IFERROR('Cash Flow'!K8, 0) -> 2008 | J77: =IFERROR('Cash Flow'!L8, 0) -> 3321 | ... L77: =IFERROR('Cash Flow'!N8, 0) -> 5194
B78: Loans Advances | C78: =IFERROR('Cash Flow'!E9, 0) -> 1 | D78: =IFERROR('Cash Flow'!F9, 0) -> 0 | E78: =IFERROR('Cash Flow'!G9, 0) -> -13 | F78: =IFERROR('Cash Flow'!H9, 0) -> -1 | G78: =IFERROR('Cash Flow'!I9, 0) -> -6 | H78: =IFERROR('Cash Flow'!J9, 0) -> -8 | I78: =IFERROR('Cash Flow'!K9, 0) -> 1 | J78: =IFERROR('Cash Flow'!L9, 0) -> -3 | ... L78: =IFERROR('Cash Flow'!N9, 0) -> -1
B79: Other WC items | C79: =IFERROR('Cash Flow'!E10, 0) -> 1222 | D79: =IFERROR('Cash Flow'!F10, 0) -> 839 | E79: =IFERROR('Cash Flow'!G10, 0) -> 569 | F79: =IFERROR('Cash Flow'!H10, 0) -> -863 | G79: =IFERROR('Cash Flow'!I10, 0) -> 801 | H79: =IFERROR('Cash Flow'!J10, 0) -> -1162 | I79: =IFERROR('Cash Flow'!K10, 0) -> 374 | J79: =IFERROR('Cash Flow'!L10, 0) -> -406 | ... L79: =IFERROR('Cash Flow'!N10, 0) -> -387
B80: Working capital changes | C80: =IFERROR('Cash Flow'!E11, 0) -> 2192 | D80: =IFERROR('Cash Flow'!F11, 0) -> 2808 | E80: =IFERROR('Cash Flow'!G11, 0) -> -1315 | F80: =IFERROR('Cash Flow'!H11, 0) -> -2570 | G80: =IFERROR('Cash Flow'!I11, 0) -> 4336 | H80: =IFERROR('Cash Flow'!J11, 0) -> -2813 | I80: =IFERROR('Cash Flow'!K11, 0) -> 373 | J80: =IFERROR('Cash Flow'!L11, 0) -> 1722 | ... L80: =IFERROR('Cash Flow'!N11, 0) -> 1635
B81: Direct taxes | C81: =IFERROR('Cash Flow'!E12, 0) -> -2323 | D81: =IFERROR('Cash Flow'!F12, 0) -> -3056 | E81: =IFERROR('Cash Flow'!G12, 0) -> -3144 | F81: =IFERROR('Cash Flow'!H12, 0) -> -1438 | G81: =IFERROR('Cash Flow'!I12, 0) -> -1011 | H81: =IFERROR('Cash Flow'!J12, 0) -> -1178 | I81: =IFERROR('Cash Flow'!K12, 0) -> -2233 | J81: =IFERROR('Cash Flow'!L12, 0) -> -3597 | ... L81: =IFERROR('Cash Flow'!N12, 0) -> -4337
B82: Cash from Operating Activities | C82: =SUM(C74:C81) -> 12475 | D82: =SUM(D74:D81) -> 14597 | E82: =SUM(E74:E81) -> 5286 | F82: =SUM(F74:F81) -> 925 | G82: =SUM(G74:G81) -> 13192 | H82: =SUM(H74:H81) -> -972 | I82: =SUM(I74:I81) -> 9626 | J82: =SUM(J74:J81) -> 18522 | ... L82: =SUM(L74:L81) -> 20735
B84: Investing Activities
B85: Fixed assets purchased | C85: =IFERROR('Cash Flow'!E14, 0) -> -3391 | D85: =IFERROR('Cash Flow'!F14, 0) -> -3912 | E85: =IFERROR('Cash Flow'!G14, 0) -> -4872 | F85: =IFERROR('Cash Flow'!H14, 0) -> -3437 | G85: =IFERROR('Cash Flow'!I14, 0) -> -2370 | H85: =IFERROR('Cash Flow'!J14, 0) -> -3459 | I85: =IFERROR('Cash Flow'!K14, 0) -> -6347 | J85: =IFERROR('Cash Flow'!L14, 0) -> -9200 | ... L85: =IFERROR('Cash Flow'!N14, 0) -> -10398
B86: Fixed assets sold | C86: =IFERROR('Cash Flow'!E15, 0) -> 16 | D86: =IFERROR('Cash Flow'!F15, 0) -> 26 | E86: =IFERROR('Cash Flow'!G15, 0) -> 170 | F86: =IFERROR('Cash Flow'!H15, 0) -> 37 | G86: =IFERROR('Cash Flow'!I15, 0) -> 42 | H86: =IFERROR('Cash Flow'!J15, 0) -> 136 | I86: =IFERROR('Cash Flow'!K15, 0) -> 100 | J86: =IFERROR('Cash Flow'!L15, 0) -> 45 | ... L86: =IFERROR('Cash Flow'!N15, 0) -> 52
B87: Investments purchased | C87: =IFERROR('Cash Flow'!E16, 0) -> -17716 | D87: =IFERROR('Cash Flow'!F16, 0) -> -47069 | E87: =IFERROR('Cash Flow'!G16, 0) -> -52957 | F87: =IFERROR('Cash Flow'!H16, 0) -> -44205 | G87: =IFERROR('Cash Flow'!I16, 0) -> -44869 | H87: =IFERROR('Cash Flow'!J16, 0) -> -60525 | I87: =IFERROR('Cash Flow'!K16, 0) -> -66597 | J87: =IFERROR('Cash Flow'!L16, 0) -> -65736 | ... L87: =IFERROR('Cash Flow'!N16, 0) -> -108034
B88: Investments sold | C88: =IFERROR('Cash Flow'!E17, 0) -> 11839 | D88: =IFERROR('Cash Flow'!F17, 0) -> 42564 | E88: =IFERROR('Cash Flow'!G17, 0) -> 53986 | F88: =IFERROR('Cash Flow'!H17, 0) -> 46969 | G88: =IFERROR('Cash Flow'!I17, 0) -> 42920 | H88: =IFERROR('Cash Flow'!J17, 0) -> 63579 | I88: =IFERROR('Cash Flow'!K17, 0) -> 61605 | J88: =IFERROR('Cash Flow'!L17, 0) -> 61933 | ... L88: =IFERROR('Cash Flow'!N17, 0) -> 101969
B89: Interest received | C89: =IFERROR('Cash Flow'!E18, 0) -> 36 | D89: =IFERROR('Cash Flow'!F18, 0) -> 68 | E89: =IFERROR('Cash Flow'!G18, 0) -> 124 | F89: =IFERROR('Cash Flow'!H18, 0) -> 96 | G89: =IFERROR('Cash Flow'!I18, 0) -> 67 | H89: =IFERROR('Cash Flow'!J18, 0) -> 174 | I89: =IFERROR('Cash Flow'!K18, 0) -> 194 | J89: =IFERROR('Cash Flow'!L18, 0) -> 372 | ... L89: =IFERROR('Cash Flow'!N18, 0) -> 354
B90: Dividends received | C90: =IFERROR('Cash Flow'!E19, 0) -> 13 | D90: =IFERROR('Cash Flow'!F19, 0) -> 20 | E90: =IFERROR('Cash Flow'!G19, 0) -> 9 | F90: =IFERROR('Cash Flow'!H19, 0) -> 4 | G90: =IFERROR('Cash Flow'!I19, 0) -> 3 | H90: =IFERROR('Cash Flow'!J19, 0) -> 3 | I90: =IFERROR('Cash Flow'!K19, 0) -> 6 | J90: =IFERROR('Cash Flow'!L19, 0) -> 6 | ... L90: =IFERROR('Cash Flow'!N19, 0) -> 11
B91: Redemp n Canc of Shares | C91: =IFERROR('Cash Flow'!E20, 0) -> 22 | D91: =IFERROR('Cash Flow'!F20, 0) -> 0 | E91: =IFERROR('Cash Flow'!G20, 0) -> 0 | F91: =IFERROR('Cash Flow'!H20, 0) -> 0 | G91: =IFERROR('Cash Flow'!I20, 0) -> 0 | H91: =IFERROR('Cash Flow'!J20, 0) -> 0 | I91: =IFERROR('Cash Flow'!K20, 0) -> 0 | J91: =IFERROR('Cash Flow'!L20, 0) -> 0 | ... L91: =IFERROR('Cash Flow'!N20, 0) -> 0
B92: Acquisition of companies | C92: =IFERROR('Cash Flow'!E21, 0) -> 0 | D92: =IFERROR('Cash Flow'!F21, 0) -> 0 | E92: =IFERROR('Cash Flow'!G21, 0) -> 0 | F92: =IFERROR('Cash Flow'!H21, 0) -> -15 | G92: =IFERROR('Cash Flow'!I21, 0) -> -65 | H92: =IFERROR('Cash Flow'!J21, 0) -> -146 | I92: =IFERROR('Cash Flow'!K21, 0) -> 0 | J92: =IFERROR('Cash Flow'!L21, 0) -> -80 | ... L92: =IFERROR('Cash Flow'!N21, 0) -> 0
B93: Other investing items | C93: =IFERROR('Cash Flow'!E22, 0) -> 7 | D93: =IFERROR('Cash Flow'!F22, 0) -> 0 | E93: =IFERROR('Cash Flow'!G22, 0) -> 0 | F93: =IFERROR('Cash Flow'!H22, 0) -> -5 | G93: =IFERROR('Cash Flow'!I22, 0) -> -3019 | H93: =IFERROR('Cash Flow'!J22, 0) -> -1 | I93: =IFERROR('Cash Flow'!K22, 0) -> 3003 | J93: =IFERROR('Cash Flow'!L22, 0) -> 795 | ... L93: =IFERROR('Cash Flow'!N22, 0) -> 1311
B94: Cash from Investing Activities | C94: =SUM(C85:C93) -> -9174 | D94: =SUM(D85:D93) -> -8303 | E94: =SUM(E85:E93) -> -3540 | F94: =SUM(F85:F93) -> -556 | G94: =SUM(G85:G93) -> -7291 | H94: =SUM(H85:H93) -> -239 | I94: =SUM(I85:I93) -> -8036 | J94: =SUM(J85:J93) -> -11865 | ... L94: =SUM(L85:L93) -> -14735
B96: Financial Activities
B97: Proceeds from borrowings | C97: =IFERROR('Cash Flow'!E24, 0) -> 484 | D97: =IFERROR('Cash Flow'!F24, 0) -> 10 | E97: =IFERROR('Cash Flow'!G24, 0) -> 39 | F97: =IFERROR('Cash Flow'!H24, 0) -> 0 | G97: =IFERROR('Cash Flow'!I24, 0) -> 380 | H97: =IFERROR('Cash Flow'!J24, 0) -> 0 | I97: =IFERROR('Cash Flow'!K24, 0) -> 831 | J97: =IFERROR('Cash Flow'!L24, 0) -> 0 | ... L97: =IFERROR('Cash Flow'!N24, 0) -> 0
B98: Repayment of borrowings | C98: =IFERROR('Cash Flow'!E25, 0) -> -231 | D98: =IFERROR('Cash Flow'!F25, 0) -> -373 | E98: =IFERROR('Cash Flow'!G25, 0) -> 0 | F98: =IFERROR('Cash Flow'!H25, 0) -> -46 | G98: =IFERROR('Cash Flow'!I25, 0) -> 0 | H98: =IFERROR('Cash Flow'!J25, 0) -> -110 | I98: =IFERROR('Cash Flow'!K25, 0) -> 0 | J98: =IFERROR('Cash Flow'!L25, 0) -> -1183 | ... L98: =IFERROR('Cash Flow'!N25, 0) -> 0
B99: Interest paid fin | C99: =IFERROR('Cash Flow'!E26, 0) -> -110 | D99: =IFERROR('Cash Flow'!F26, 0) -> -346 | E99: =IFERROR('Cash Flow'!G26, 0) -> -73 | F99: =IFERROR('Cash Flow'!H26, 0) -> -136 | G99: =IFERROR('Cash Flow'!I26, 0) -> -102 | H99: =IFERROR('Cash Flow'!J26, 0) -> -130 | I99: =IFERROR('Cash Flow'!K26, 0) -> -186 | J99: =IFERROR('Cash Flow'!L26, 0) -> -147 | ... L99: =IFERROR('Cash Flow'!N26, 0) -> -204
B100: Dividends paid | C100: =IFERROR('Cash Flow'!E27, 0) -> -1057 | D100: =IFERROR('Cash Flow'!F27, 0) -> -2266 | E100: =IFERROR('Cash Flow'!G27, 0) -> -2417 | F100: =IFERROR('Cash Flow'!H27, 0) -> -2417 | G100: =IFERROR('Cash Flow'!I27, 0) -> -1812 | H100: =IFERROR('Cash Flow'!J27, 0) -> -1359 | I100: =IFERROR('Cash Flow'!K27, 0) -> -1812 | J100: =IFERROR('Cash Flow'!L27, 0) -> -2719 | ... L100: =IFERROR('Cash Flow'!N27, 0) -> -4244
B101: Financial liabilities | C101: =IFERROR('Cash Flow'!E28, 0) -> 0 | D101: =IFERROR('Cash Flow'!F28, 0) -> 0 | E101: =IFERROR('Cash Flow'!G28, 0) -> 0 | F101: =IFERROR('Cash Flow'!H28, 0) -> -10 | G101: =IFERROR('Cash Flow'!I28, 0) -> -11 | H101: =IFERROR('Cash Flow'!J28, 0) -> -8 | I101: =IFERROR('Cash Flow'!K28, 0) -> -46 | J101: =IFERROR('Cash Flow'!L28, 0) -> -13 | ... L101: =IFERROR('Cash Flow'!N28, 0) -> -36
B102: Other financing items | C102: =IFERROR('Cash Flow'!E29, 0) -> -215 | D102: =IFERROR('Cash Flow'!F29, 0) -> -461 | E102: =IFERROR('Cash Flow'!G29, 0) -> -497 | F102: =IFERROR('Cash Flow'!H29, 0) -> -497 | G102: =IFERROR('Cash Flow'!I29, 0) -> 0 | H102: =IFERROR('Cash Flow'!J29, 0) -> 0 | I102: =IFERROR('Cash Flow'!K29, 0) -> 0 | J102: =IFERROR('Cash Flow'!L29, 0) -> 0 | ... L102: =IFERROR('Cash Flow'!N29, 0) -> 0
B103: Cash from Financial Activites | C103: =SUM(C97:C102) -> -1129 | D103: =SUM(D97:D102) -> -3436 | E103: =SUM(E97:E102) -> -2948 | F103: =SUM(F97:F102) -> -3106 | G103: =SUM(G97:G102) -> -1545 | H103: =SUM(H97:H102) -> -1607 | I103: =SUM(I97:I102) -> -1213 | J103: =SUM(J97:J102) -> -4062 | ... L103: =SUM(L97:L102) -> -4484
B105: Net Cash Flow | C105: =IFERROR(C82+C94+C103,0) -> 2172 | D105: =IFERROR(D82+D94+D103,0) -> 2858 | E105: =IFERROR(E82+E94+E103,0) -> -1202 | F105: =IFERROR(F82+F94+F103,0) -> -2737 | G105: =IFERROR(G82+G94+G103,0) -> 4356 | H105: =IFERROR(H82+H94+H103,0) -> -2818 | I105: =IFERROR(I82+I94+I103,0) -> 377 | J105: =IFERROR(J82+J94+J103,0) -> 2595 | ... L105: =IFERROR(L82+L94+L103,0) -> 1516

Sheet Ratio Analysis
B2: ="Ratio Analysis - "&'Data Sheet'!B1 -> Ratio Analysis - MARUTI SUZUKI INDIA LTD
B3: Years | C3: ='Data Sheet'!B16 -> 42825 | D3: ='Data Sheet'!C16 -> 43190 | E3: ='Data Sheet'!D16 -> 43555 | F3: ='Data Sheet'!E16 -> 43921 | G3: ='Data Sheet'!F16 -> 44286 | H3: ='Data Sheet'!G16 -> 44651 | I3: ='Data Sheet'!H16 -> 45016 | J3: ='Data Sheet'!I16 -> 45382 | ... L3: ='Data Sheet'!K16 -> 46112 | M3: Trend | N3: Mean | O3: Median
B5: Sales Growth | D5: =IFERROR('Historical FS'!D8,0) -> 0.17220239 | E5: =IFERROR('Historical FS'!E8,0) -> 0.078425599 | F5: =IFERROR('Historical FS'!F8,0) -> -0.12093275 | G5: =IFERROR('Historical FS'!G8,0) -> -0.06989162 | H5: =IFERROR('Historical FS'!H8,0) -> 0.25518388 | I5: =IFERROR('Historical FS'!I8,0) -> 0.33104909 | J5: =IFERROR('Historical FS'!J8,0) -> 0.20657167 | K5: =IFERROR('Historical FS'!K8,0) -> 0.077928523 | L5: =IFERROR('Historical FS'!L8,0) -> 0.19882548 | N5: =IFERROR(AVERAGE(D5:L5),0) -> 0.1254847 | O5: =IFERROR(MEDIAN(D5:L5),0) -> 0.17220239
B6: EBITDA Growth | D6: =IFERROR('Historical FS'!D19/'Historical FS'!C19-1, 0) -> 0.17565314 | E6: =IFERROR('Historical FS'!E19/'Historical FS'!D19-1, 0) -> 0.056023399 | F6: =IFERROR('Historical FS'!F19/'Historical FS'!E19-1, 0) -> -0.1352951 | G6: =IFERROR('Historical FS'!G19/'Historical FS'!F19-1, 0) -> -0.061620895 | H6: =IFERROR('Historical FS'!H19/'Historical FS'!G19-1, 0) -> 0.2709264 | I6: =IFERROR('Historical FS'!I19/'Historical FS'!H19-1, 0) -> 0.34335638 | J6: =IFERROR('Historical FS'!J19/'Historical FS'!I19-1, 0) -> 0.21907832 | K6: =IFERROR('Historical FS'!K19/'Historical FS'!J19-1, 0) -> 0.088582663 | L6: =IFERROR('Historical FS'!L19/'Historical FS'!K19-1, 0) -> 0.19268394 | N6: =IFERROR(AVERAGE(D6:L6),0) -> 0.12770981 | O6: =IFERROR(MEDIAN(D6:L6),0) -> 0.17565314
B7: EBIT Growth | D7: =IFERROR('Historical FS'!D28/'Historical FS'!C28-1, 0) -> 0.17671559 | E7: =IFERROR('Historical FS'!E28/'Historical FS'!D28-1, 0) -> 0.058739913 | F7: =IFERROR('Historical FS'!F28/'Historical FS'!E28-1, 0) -> -0.14911228 | G7: =IFERROR('Historical FS'!G28/'Historical FS'!F28-1, 0) -> -0.056657873 | H7: =IFERROR('Historical FS'!H28/'Historical FS'!G28-1, 0) -> 0.28962644 | I7: =IFERROR('Historical FS'!I28/'Historical FS'!H28-1, 0) -> 0.35560817 | J7: =IFERROR('Historical FS'!J28/'Historical FS'!I28-1, 0) -> 0.2013155 | K7: =IFERROR('Historical FS'!K28/'Historical FS'!J28-1, 0) -> 0.089662255 | L7: =IFERROR('Historical FS'!L28/'Historical FS'!K28-1, 0) -> 0.19222591 | N7: =IFERROR(AVERAGE(D7:L7),0) -> 0.1286804 | O7: =IFERROR(MEDIAN(D7:L7),0) -> 0.17671559
B8: Net Profit Growth | D8: =IFERROR('Historical FS'!D34/'Historical FS'!C34-1, 0) -> 0.1729118 | E8: =IFERROR('Historical FS'!E34/'Historical FS'!D34-1, 0) -> 0.066641994 | F8: =IFERROR('Historical FS'!F34/'Historical FS'!E34-1, 0) -> -0.1329399 | G8: =IFERROR('Historical FS'!G34/'Historical FS'!F34-1, 0) -> -0.049692021 | H8: =IFERROR('Historical FS'!H34/'Historical FS'!G34-1, 0) -> 0.29645107 | I8: =IFERROR('Historical FS'!I34/'Historical FS'!H34-1, 0) -> 0.34185367 | J8: =IFERROR('Historical FS'!J34/'Historical FS'!I34-1, 0) -> 0.18702693 | K8: =IFERROR('Historical FS'!K34/'Historical FS'!J34-1, 0) -> 0.082515935 | L8: =IFERROR('Historical FS'!L34/'Historical FS'!K34-1, 0) -> 0.20545955 | N8: =IFERROR(AVERAGE(D8:L8),0) -> 0.13002545 | O8: =IFERROR(MEDIAN(D8:L8),0) -> 0.1729118
B9: Dividend Growth | D9: =IFERROR('Historical FS'!D42/'Historical FS'!C42-1,0) -> 0.066666667 | E9: =IFERROR('Historical FS'!E42/'Historical FS'!D42-1,0) -> 0 | F9: =IFERROR('Historical FS'!F42/'Historical FS'!E42-1,0) -> -0.25 | G9: =IFERROR('Historical FS'!G42/'Historical FS'!F42-1,0) -> -0.25 | H9: =IFERROR('Historical FS'!H42/'Historical FS'!G42-1,0) -> 0.33333333 | I9: =IFERROR('Historical FS'!I42/'Historical FS'!H42-1,0) -> 0.5 | J9: =IFERROR('Historical FS'!J42/'Historical FS'!I42-1,0) -> 0.38934879 | K9: =IFERROR('Historical FS'!K42/'Historical FS'!J42-1,0) -> 0.08 | L9: =IFERROR('Historical FS'!L42/'Historical FS'!K42-1,0) -> 0.037037037 | N9: =IFERROR(AVERAGE(D9:L9),0) -> 0.10070954 | O9: =IFERROR(MEDIAN(D9:L9),0) -> 0.066666667
B11: Gross Margin | C11: =IFERROR('Historical FS'!C14,0) -> 0.99238305 | D11: =IFERROR('Historical FS'!D14,0) -> 0.9915624 | E11: =IFERROR('Historical FS'!E14,0) -> 0.98996962 | F11: =IFERROR('Historical FS'!F14,0) -> 0.99075469 | G11: =IFERROR('Historical FS'!G14,0) -> 0.99322742 | H11: =IFERROR('Historical FS'!H14,0) -> 0.99285745 | I11: =IFERROR('Historical FS'!I14,0) -> 0.99328067 | J11: =IFERROR('Historical FS'!J14,0) -> 0.99271526 | ... L11: =IFERROR('Historical FS'!L14,0) -> 1 | N11: =IFERROR(AVERAGE(C11:L11),0) -> 0.99298669 | O11: =IFERROR(MEDIAN(C11:L11),0) -> 0.99278636
B12: EBITDA Margin | C12: =IFERROR('Historical FS'!C20,0) -> 0.87988103 | D12: =IFERROR('Historical FS'!D20,0) -> 0.88247124 | E12: =IFERROR('Historical FS'!E20,0) -> 0.86413961 | F12: =IFERROR('Historical FS'!F20,0) -> 0.85002115 | G12: =IFERROR('Historical FS'!G20,0) -> 0.85757972 | H12: =IFERROR('Historical FS'!H20,0) -> 0.86833549 | I12: =IFERROR('Historical FS'!I20,0) -> 0.87636438 | J12: =IFERROR('Historical FS'!J20,0) -> 0.88544829 | ... L12: =IFERROR('Historical FS'!L20,0) -> 0.88961902 | N12: =IFERROR(AVERAGE(C12:L12),0) -> 0.87480599 | O12: =IFERROR(MEDIAN(C12:L12),0) -> 0.87812271
B13: EBIT Margin | C13: =IFERROR(('Historical FS'!C19-'Historical FS'!C25)/'Historical FS'!C7,0) -> 0.84163619 | D13: =IFERROR(('Historical FS'!D19-'Historical FS'!D25)/'Historical FS'!D7,0) -> 0.84789135 | E13: =IFERROR(('Historical FS'!E19-'Historical FS'!E25)/'Historical FS'!E7,0) -> 0.82904198 | F13: =IFERROR(('Historical FS'!F19-'Historical FS'!F25)/'Historical FS'!F7,0) -> 0.8033862 | G13: =IFERROR(('Historical FS'!G19-'Historical FS'!G25)/'Historical FS'!G7,0) -> 0.81446456 | H13: =IFERROR(('Historical FS'!H19-'Historical FS'!H25)/'Historical FS'!H7,0) -> 0.83676064 | I13: =IFERROR(('Historical FS'!I19-'Historical FS'!I25)/'Historical FS'!I7,0) -> 0.85233046 | J13: =IFERROR(('Historical FS'!J19-'Historical FS'!J25)/'Historical FS'!J7,0) -> 0.84839861 | ... L13: =IFERROR(('Historical FS'!L19-'Historical FS'!L25)/'Historical FS'!L7,0) -> 0.85284263 | N13: =IFERROR(AVERAGE(C13:L13),0) -> 0.83842768 | O13: =IFERROR(MEDIAN(C13:L13),0) -> 0.84476377
B14: EBT Margin | C14: =IFERROR('Historical FS'!C29,0) -> 0.84032313 | D14: =IFERROR('Historical FS'!D29,0) -> 0.84355853 | E14: =IFERROR('Historical FS'!E29,0) -> 0.82816013 | F14: =IFERROR('Historical FS'!F29,0) -> 0.80161248 | G14: =IFERROR('Historical FS'!G29,0) -> 0.81301796 | H14: =IFERROR('Historical FS'!H29,0) -> 0.83532738 | I14: =IFERROR('Historical FS'!I29,0) -> 0.85073993 | J14: =IFERROR('Historical FS'!J29,0) -> 0.84703387 | ... L14: =IFERROR('Historical FS'!L29,0) -> 0.85154051 | N14: =IFERROR(AVERAGE(C14:L14),0) -> 0.83675681 | O14: =IFERROR(MEDIAN(C14:L14),0) -> 0.84194083
B15: Net Profit Margin | C15: =IFERROR('Historical FS'!C35,0) -> 0.80189763 | D15: =IFERROR('Historical FS'!D35,0) -> 0.80238293 | E15: =IFERROR('Historical FS'!E35,0) -> 0.79361555 | F15: =IFERROR('Historical FS'!F35,0) -> 0.78277557 | G15: =IFERROR('Historical FS'!G35,0) -> 0.79977548 | H15: =IFERROR('Historical FS'!H35,0) -> 0.82607002 | I15: =IFERROR('Historical FS'!I35,0) -> 0.83277552 | J15: =IFERROR('Historical FS'!J35,0) -> 0.81928574 | ... L15: =IFERROR('Historical FS'!L35,0) -> 0.82732549 | N15: =IFERROR(AVERAGE(C15:L15),0) -> 0.81086764 | O15: =IFERROR(MEDIAN(C15:L15),0) -> 0.81083433
B17: Sales Expenses % Sales | C17: =IFERROR('Historical FS'!C17,0) -> 0.11250202 | D17: =IFERROR('Historical FS'!D17,0) -> 0.10909116 | E17: =IFERROR('Historical FS'!E17,0) -> 0.12583001 | F17: =IFERROR('Historical FS'!F17,0) -> 0.14073354 | G17: =IFERROR('Historical FS'!G17,0) -> 0.1356477 | H17: =IFERROR('Historical FS'!H17,0) -> 0.12452196 | I17: =IFERROR('Historical FS'!I17,0) -> 0.11691629 | J17: =IFERROR('Historical FS'!J17,0) -> 0.10726698 | ... L17: =IFERROR('Historical FS'!L17,0) -> 0.11038098 | N17: =IFERROR(AVERAGE(C17:L17),0) -> 0.1181807 | O17: =IFERROR(MEDIAN(C17:L17),0) -> 0.11470915
B18: Depreciation % Sales | C18: =IFERROR('Historical FS'!C26,0) -> 0.038244841 | D18: =IFERROR('Historical FS'!D26,0) -> 0.034579887 | E18: =IFERROR('Historical FS'!E26,0) -> 0.035097626 | F18: =IFERROR('Historical FS'!F26,0) -> 0.046634946 | G18: =IFERROR('Historical FS'!G26,0) -> 0.043115159 | H18: =IFERROR('Historical FS'!H26,0) -> 0.031574848 | I18: =IFERROR('Historical FS'!I26,0) -> 0.024033927 | J18: =IFERROR('Historical FS'!J26,0) -> 0.037049674 | ... L18: =IFERROR('Historical FS'!L26,0) -> 0.036776386 | N18: =IFERROR(AVERAGE(C18:L18),0) -> 0.036378305 | O18: =IFERROR(MEDIAN(C18:L18),0) -> 0.036726071
B19: Operating Income % Sales | C19: =C13 -> 0.84163619 | D19: =D13 -> 0.84789135 | E19: =E13 -> 0.82904198 | F19: =F13 -> 0.8033862 | G19: =G13 -> 0.81446456 | H19: =H13 -> 0.83676064 | I19: =I13 -> 0.85233046 | J19: =J13 -> 0.84839861 | ... L19: =L13 -> 0.85284263 | N19: =IFERROR(AVERAGE(C19:L19),0) -> 0.83842768 | O19: =IFERROR(MEDIAN(C19:L19),0) -> 0.84476377
B21: Return on Capital Employed | C21: =IFERROR(('Historical FS'!C19-'Historical FS'!C25)/SUM('Historical FS'!C50,'Historical FS'!C51,'Historical FS'!C52),0) -> 1.5256865 | D21: =IFERROR(('Historical FS'!D19-'Historical FS'!D25)/SUM('Historical FS'!D50,'Historical FS'!D51,'Historical FS'!D52),0) -> 1.5855057 | E21: =IFERROR(('Historical FS'!E19-'Historical FS'!E25)/SUM('Historical FS'!E50,'Historical FS'!E51,'Historical FS'!E52),0) -> 1.5100917 | F21: =IFERROR(('Historical FS'!F19-'Historical FS'!F25)/SUM('Historical FS'!F50,'Historical FS'!F51,'Historical FS'!F52),0) -> 1.2255596 | G21: =IFERROR(('Historical FS'!G19-'Historical FS'!G25)/SUM('Historical FS'!G50,'Historical FS'!G51,'Historical FS'!G52),0) -> 1.0805784 | H21: =IFERROR(('Historical FS'!H19-'Historical FS'!H25)/SUM('Historical FS'!H50,'Historical FS'!H51,'Historical FS'!H52),0) -> 1.3255421 | I21: =IFERROR(('Historical FS'!I19-'Historical FS'!I25)/SUM('Historical FS'!I50,'Historical FS'!I51,'Historical FS'!I52),0) -> 1.5896546 | J21: =IFERROR(('Historical FS'!J19-'Historical FS'!J25)/SUM('Historical FS'!J50,'Historical FS'!J51,'Historical FS'!J52),0) -> 1.4034501 | ... L21: =IFERROR(('Historical FS'!L19-'Historical FS'!L25)/SUM('Historical FS'!L50,'Historical FS'!L51,'Historical FS'!L52),0) -> 1.4575932 | N21: =IFERROR(AVERAGE(C21:L21),0) -> 1.4064928 | O21: =IFERROR(MEDIAN(C21:L21),0) -> 1.4305217
B22: Retained Earnings % | C22: =IFERROR('Historical FS'!C45,0) -> 0.95851436 | D22: =IFERROR('Historical FS'!D45,0) -> 0.96227222 | E22: =IFERROR('Historical FS'!E45,0) -> 0.96462939 | F22: =IFERROR('Historical FS'!F45,0) -> 0.96940471 | G22: =IFERROR('Historical FS'!G45,0) -> 0.97585365 | H22: =IFERROR('Historical FS'!H45,0) -> 0.97516672 | I22: =IFERROR('Historical FS'!I45,0) -> 0.97223995 | J22: =IFERROR('Historical FS'!J45,0) -> 0.96618552 | ... L22: =IFERROR('Historical FS'!L45,0) -> 0.97097757 | N22: =IFERROR(AVERAGE(C22:L22),0) -> 0.96815082 | O22: =IFERROR(MEDIAN(C22:L22),0) -> 0.96783441
B23: Return on Equity | C23: =IFERROR('Historical FS'!C34/SUM('Historical FS'!C50:C51),0) -> 1.472611 | D23: =IFERROR('Historical FS'!D34/SUM('Historical FS'!D50:D51),0) -> 1.5046664 | E23: =IFERROR('Historical FS'!E34/SUM('Historical FS'!E50:E51),0) -> 1.450462 | F23: =IFERROR('Historical FS'!F34/SUM('Historical FS'!F50:F51),0) -> 1.1985672 | G23: =IFERROR('Historical FS'!G34/SUM('Historical FS'!G50:G51),0) -> 1.072022 | H23: =IFERROR('Historical FS'!H34/SUM('Historical FS'!H50:H51),0) -> 1.3186695 | I23: =IFERROR('Historical FS'!I34/SUM('Historical FS'!I50:I51),0) -> 1.5845354 | J23: =IFERROR('Historical FS'!J34/SUM('Historical FS'!J50:J51),0) -> 1.3571675 | ... L23: =IFERROR('Historical FS'!L34/SUM('Historical FS'!L50:L51),0) -> 1.4153344 | N23: =IFERROR(AVERAGE(C23:L23),0) -> 1.3681317 | O23: =IFERROR(MEDIAN(C23:L23),0) -> 1.386251
B24: Self Sustained Growth Rate | C24: =IFERROR(C23*C22,0) -> 1.4115188 | D24: =IFERROR(D23*D22,0) -> 1.4478987 | E24: =IFERROR(E23*E22,0) -> 1.3991582 | F24: =IFERROR(F23*F22,0) -> 1.1618967 | G24: =IFERROR(G23*G22,0) -> 1.0461366 | H24: =IFERROR(H23*H22,0) -> 1.2859226 | I24: =IFERROR(I23*I22,0) -> 1.5405486 | J24: =IFERROR(J23*J22,0) -> 1.3112756 | ... L24: =IFERROR(L23*L22,0) -> 1.374258 | N24: =IFERROR(AVERAGE(C24:L24),0) -> 1.3241793 | O24: =IFERROR(MEDIAN(C24:L24),0) -> 1.3427668
B25: Interested Coverage Ratio | C25: =IFERROR(('Historical FS'!C19-'Historical FS'!C25)/'Historical FS'!C22,0) -> 640.97092 | D25: =IFERROR(('Historical FS'!D19-'Historical FS'!D25)/'Historical FS'!D22,0) -> 195.69028 | E25: =IFERROR(('Historical FS'!E19-'Historical FS'!E25)/'Historical FS'!E22,0) -> 940.11067 | F25: =IFERROR(('Historical FS'!F19-'Historical FS'!F25)/'Historical FS'!F22,0) -> 452.93741 | G25: =IFERROR(('Historical FS'!G19-'Historical FS'!G25)/'Historical FS'!G22,0) -> 563.02063 | H25: =IFERROR(('Historical FS'!H19-'Historical FS'!H25)/'Historical FS'!H22,0) -> 583.81438 | I25: =IFERROR(('Historical FS'!I19-'Historical FS'!I25)/'Historical FS'!I22,0) -> 535.88021 | J25: =IFERROR(('Historical FS'!J19-'Historical FS'!J25)/'Historical FS'!J22,0) -> 621.65444 | ... L25: =IFERROR(('Historical FS'!L19-'Historical FS'!L25)/'Historical FS'!L22,0) -> 654.96313 | N25: =IFERROR(AVERAGE(C25:L25),0) -> 586.42563 | O25: =IFERROR(MEDIAN(C25:L25),0) -> 602.73441
B27: Debtor Turnover Ratio | C27: =IFERROR('Historical FS'!C7/'Historical FS'!C62,0) -> 56.614835 | D27: =IFERROR('Historical FS'!D7/'Historical FS'!D62,0) -> 54.462536 | E27: =IFERROR('Historical FS'!E7/'Historical FS'!E62,0) -> 37.213983 | F27: =IFERROR('Historical FS'!F7/'Historical FS'!F62,0) -> 38.256561 | G27: =IFERROR('Historical FS'!G7/'Historical FS'!G62,0) -> 54.982421 | H27: =IFERROR('Historical FS'!H7/'Historical FS'!H62,0) -> 43.415974 | I27: =IFERROR('Historical FS'!I7/'Historical FS'!I62,0) -> 35.612558 | J27: =IFERROR('Historical FS'!J7/'Historical FS'!J62,0) -> 30.860207 | ... L27: =IFERROR('Historical FS'!L7/'Historical FS'!L62,0) -> 34.315987 | N27: =IFERROR(AVERAGE(C27:L27),0) -> 40.911733 | O27: =IFERROR(MEDIAN(C27:L27),0) -> 37.735272
B28: Creditor Turnover Ratio | C28: =IFERROR('Historical FS'!C7/'Historical FS'!C53,0) -> 4.7275341 | D28: =IFERROR('Historical FS'!D7/'Historical FS'!D53,0) -> 4.5428331 | E28: =IFERROR('Historical FS'!E7/'Historical FS'!E53,0) -> 5.1485613 | F28: =IFERROR('Historical FS'!F7/'Historical FS'!F53,0) -> 5.3924993 | G28: =IFERROR('Historical FS'!G7/'Historical FS'!G53,0) -> 3.8382075 | H28: =IFERROR('Historical FS'!H7/'Historical FS'!H53,0) -> 4.6744 | I28: =IFERROR('Historical FS'!I7/'Historical FS'!I53,0) -> 5.4536443 | J28: =IFERROR('Historical FS'!J7/'Historical FS'!J53,0) -> 4.8006971 | ... L28: =IFERROR('Historical FS'!L7/'Historical FS'!L53,0) -> 4.4042843 | N28: =IFERROR(AVERAGE(C28:L28),0) -> 4.7272632 | O28: =IFERROR(MEDIAN(C28:L28),0) -> 4.700967
B29: Inventory Turnover | C29: =IFERROR('Historical FS'!C7/'Historical FS'!C63,0) -> 20.861292 | D29: =IFERROR('Historical FS'!D7/'Historical FS'!D63,0) -> 25.254541 | E29: =IFERROR('Historical FS'!E7/'Historical FS'!E63,0) -> 25.903961 | F29: =IFERROR('Historical FS'!F7/'Historical FS'!F63,0) -> 23.541492 | G29: =IFERROR('Historical FS'!G7/'Historical FS'!G63,0) -> 23.080354 | H29: =IFERROR('Historical FS'!H7/'Historical FS'!H63,0) -> 25.006313 | I29: =IFERROR('Historical FS'!I7/'Historical FS'!I63,0) -> 27.447485 | J29: =IFERROR('Historical FS'!J7/'Historical FS'!J63,0) -> 26.674602 | ... L29: =IFERROR('Historical FS'!L7/'Historical FS'!L63,0) -> 16.193135 | N29: =IFERROR(AVERAGE(C29:L29),0) -> 23.608216 | O29: =IFERROR(MEDIAN(C29:L29),0) -> 24.273902
B30: Fixed Asset Turnover | C30: =IFERROR('Historical FS'!C7/'Historical FS'!C56,0) -> 5.1150578 | D30: =IFERROR('Historical FS'!D7/'Historical FS'!D56,0) -> 5.9609076 | E30: =IFERROR('Historical FS'!E7/'Historical FS'!E56,0) -> 5.5753597 | F30: =IFERROR('Historical FS'!F7/'Historical FS'!F56,0) -> 4.8055182 | G30: =IFERROR('Historical FS'!G7/'Historical FS'!G56,0) -> 4.6950036 | H30: =IFERROR('Historical FS'!H7/'Historical FS'!H56,0) -> 6.4252939 | I30: =IFERROR('Historical FS'!I7/'Historical FS'!I56,0) -> 6.5938678 | J30: =IFERROR('Historical FS'!J7/'Historical FS'!J56,0) -> 5.0909463 | ... L30: =IFERROR('Historical FS'!L7/'Historical FS'!L56,0) -> 5.2442827 | N30: =IFERROR(AVERAGE(C30:L30),0) -> 5.4142395 | O30: =IFERROR(MEDIAN(C30:L30),0) -> 5.1796703
B31: Capital Turnover Ratio | C31: =IFERROR('Historical FS'!C7/SUM('Historical FS'!C50,'Historical FS'!C51),0) -> 1.8364077 | D31: =IFERROR('Historical FS'!D7/SUM('Historical FS'!D50,'Historical FS'!D51),0) -> 1.8752473 | E31: =IFERROR('Historical FS'!E7/SUM('Historical FS'!E50,'Historical FS'!E51),0) -> 1.8276632 | F31: =IFERROR('Historical FS'!F7/SUM('Historical FS'!F50,'Historical FS'!F51),0) -> 1.531176 | G31: =IFERROR('Historical FS'!G7/SUM('Historical FS'!G50,'Historical FS'!G51),0) -> 1.3404037 | H31: =IFERROR('Historical FS'!H7/SUM('Historical FS'!H50,'Historical FS'!H51),0) -> 1.5963169 | I31: =IFERROR('Historical FS'!I7/SUM('Historical FS'!I50,'Historical FS'!I51),0) -> 1.9027161 | J31: =IFERROR('Historical FS'!J7/SUM('Historical FS'!J50,'Historical FS'!J51),0) -> 1.6565253 | ... L31: =IFERROR('Historical FS'!L7/SUM('Historical FS'!L50,'Historical FS'!L51),0) -> 1.7107347 | N31: =IFERROR(AVERAGE(C31:L31),0) -> 1.6866064 | O31: =IFERROR(MEDIAN(C31:L31),0) -> 1.68363
B33: (in days)
B34: Debtor Days | C34: =IFERROR(365/C27,0) -> 6.4470735 | D34: =IFERROR(365/D27,0) -> 6.7018547 | E34: =IFERROR(365/E27,0) -> 9.8081412 | F34: =IFERROR(365/F27,0) -> 9.5408472 | G34: =IFERROR(365/G27,0) -> 6.6384855 | H34: =IFERROR(365/H27,0) -> 8.4070438 | I34: =IFERROR(365/I27,0) -> 10.249193 | J34: =IFERROR(365/J27,0) -> 11.827529 | ... L34: =IFERROR(365/L27,0) -> 10.636442 | N34: =IFERROR(AVERAGE(C34:L34),0) -> 9.5866732 | O34: =IFERROR(MEDIAN(C34:L34),0) -> 9.6744942
B35: Payable Days | C35: =IFERROR(365/C28,0) -> 77.20727 | D35: =IFERROR(365/D28,0) -> 80.346338 | E35: =IFERROR(365/E28,0) -> 70.893591 | F35: =IFERROR(365/F28,0) -> 67.686611 | G35: =IFERROR(365/G28,0) -> 95.096473 | H35: =IFERROR(365/H28,0) -> 78.084888 | I35: =IFERROR(365/I28,0) -> 66.927724 | J35: =IFERROR(365/J28,0) -> 76.030624 | ... L35: =IFERROR(365/L28,0) -> 82.873852 | N35: =IFERROR(AVERAGE(C35:L35),0) -> 78.022954 | O35: =IFERROR(MEDIAN(C35:L35),0) -> 77.646079
B36: Inventory Days | C36: =IFERROR(365/C29,0) -> 17.496519 | D36: =IFERROR(365/D29,0) -> 14.452846 | E36: =IFERROR(365/E29,0) -> 14.090509 | F36: =IFERROR(365/F29,0) -> 15.50454 | G36: =IFERROR(365/G29,0) -> 15.814315 | H36: =IFERROR(365/H29,0) -> 14.596314 | I36: =IFERROR(365/I29,0) -> 13.298122 | J36: =IFERROR(365/J29,0) -> 13.683428 | ... L36: =IFERROR(365/L29,0) -> 22.540417 | N36: =IFERROR(AVERAGE(C36:L36),0) -> 15.797867 | O36: =IFERROR(MEDIAN(C36:L36),0) -> 15.050427
B37: Cash Conversion Cycle | C37: =IFERROR(SUM(C34,C36)-C35,0) -> -53.263678 | D37: =IFERROR(SUM(D34,D36)-D35,0) -> -59.191637 | E37: =IFERROR(SUM(E34,E36)-E35,0) -> -46.99494 | F37: =IFERROR(SUM(F34,F36)-F35,0) -> -42.641224 | G37: =IFERROR(SUM(G34,G36)-G35,0) -> -72.643672 | H37: =IFERROR(SUM(H34,H36)-H35,0) -> -55.08153 | I37: =IFERROR(SUM(I34,I36)-I35,0) -> -43.380408 | J37: =IFERROR(SUM(J34,J36)-J35,0) -> -50.519667 | ... L37: =IFERROR(SUM(L34,L36)-L35,0) -> -49.696993 | N37: =IFERROR(AVERAGE(C37:L37),0) -> -52.638414 | O37: =IFERROR(MEDIAN(C37:L37),0) -> -51.745028
B39: CFO/Sales | C39: =IFERROR('Historical FS'!C94/'Historical FS'!C7,0) -> -0.13474334 | D39: =IFERROR('Historical FS'!D94/'Historical FS'!D7,0) -> -0.10403536 | E39: =IFERROR('Historical FS'!E94/'Historical FS'!E7,0) -> -0.04113003 | F39: =IFERROR('Historical FS'!F94/'Historical FS'!F7,0) -> -0.0073486651 | G39: =IFERROR('Historical FS'!G94/'Historical FS'!G7,0) -> -0.10360655 | H39: =IFERROR('Historical FS'!H94/'Historical FS'!H7,0) -> -0.0027057686 | I39: =IFERROR('Historical FS'!I94/'Historical FS'!I7,0) -> -0.068350014 | J39: =IFERROR('Historical FS'!J94/'Historical FS'!J7,0) -> -0.08363986 | ... L39: =IFERROR('Historical FS'!L94/'Historical FS'!L7,0) -> -0.080380327 | N39: =IFERROR(AVERAGE(C39:L39),0) -> -0.072047733 | O39: =IFERROR(MEDIAN(C39:L39),0) -> -0.082010093
B40: CFO/Fixed Assets | C40: =IFERROR('Historical FS'!C82/'Historical FS'!C67,0) -> 0.24008622 | D40: =IFERROR('Historical FS'!D82/'Historical FS'!D67,0) -> 0.24228029 | E40: =IFERROR('Historical FS'!E82/'Historical FS'!E67,0) -> 0.082634163 | F40: =IFERROR('Historical FS'!F82/'Historical FS'!F67,0) -> 0.014537693 | G40: =IFERROR('Historical FS'!G82/'Historical FS'!G67,0) -> 0.18482377 | H40: =IFERROR('Historical FS'!H82/'Historical FS'!H67,0) -> -0.013019804 | I40: =IFERROR('Historical FS'!I82/'Historical FS'!I67,0) -> 0.11378668 | J40: =IFERROR('Historical FS'!J82/'Historical FS'!J67,0) -> 0.16063609 | ... L40: =IFERROR('Historical FS'!L82/'Historical FS'!L67,0) -> 0.1392723 | N40: =IFERROR(AVERAGE(C40:L40),0) -> 0.12844498 | O40: =IFERROR(MEDIAN(C40:L40),0) -> 0.12934236
B41: CFO/Total Debt | C41: =IFERROR('Historical FS'!C82/'Historical FS'!C52,0) -> 25.796112 | D41: =IFERROR('Historical FS'!D82/'Historical FS'!D52,0) -> 120.83609 | E41: =IFERROR('Historical FS'!E82/'Historical FS'!E52,0) -> 33.120301 | F41: =IFERROR('Historical FS'!F82/'Historical FS'!F52,0) -> 5.0244432 | G41: =IFERROR('Historical FS'!G82/'Historical FS'!G52,0) -> 24.388981 | H41: =IFERROR('Historical FS'!H82/'Historical FS'!H52,0) -> -2.2843713 | I41: =IFERROR('Historical FS'!I82/'Historical FS'!I52,0) -> 7.7174697 | J41: =IFERROR('Historical FS'!J82/'Historical FS'!J52,0) -> 156.17201 | ... L41: =IFERROR('Historical FS'!L82/'Historical FS'!L52,0) -> 202.29268 | N41: =IFERROR(AVERAGE(C41:L41),0) -> 75.420165 | O41: =IFERROR(MEDIAN(C41:L41),0) -> 29.458207

Sheet Forecast
B2: ='Data Sheet'!$B$1&" - "&'Data Sheet'!A17&" Forecasting" -> MARUTI SUZUKI INDIA LTD - Sales Forecasting | G2: ='Data Sheet'!$B$1&" - "&'Historical FS'!B19 & " Forecasting " -> MARUTI SUZUKI INDIA LTD - EBITDA Forecasting | L2: ='Data Sheet'!$B$1&" - "&'Historical FS'!B39 & " Forecasting " -> MARUTI SUZUKI INDIA LTD - EPS Forecasting
B3: Year Weight | C3: Year | D3: Sales | E3: Sales Growth | G3: Year Weight | H3: Year | I3: EBITDA | J3: Sales Growth | L3: Year Weight | M3: Year | N3: EPS | O3: Sales Growth
B4: 1 | C4: ='Data Sheet'!$B$16 -> 42825 | D4: {=TRANSPOSE('Data Sheet'!B17:K17)} -> 68085 | G4: 1 | H4: ='Data Sheet'!$B$16 -> 42825 | I4: {=TRANSPOSE('Historical FS'!C19:L19)} -> 59906.7 | L4: 1 | M4: ='Data Sheet'!$B$16 -> 42825 | N4: {=TRANSPOSE('Historical FS'!C39:L39)} -> 1807.2559
B5: =B4+1 -> 2 | C5: =C4+365 -> 43190 | D5: 79809.4 | E5: =D5/D4-1 -> 0.17220239 | G5: =G4+1 -> 2 | H5: =H4+365 -> 43190 | I5: 70429.5 | J5: =I5/I4-1 -> 0.17565314 | L5: =L4+1 -> 2 | M5: =M4+365 -> 43190 | N5: 2119.7517 | O5: =N5/N4-1 -> 0.1729118
B6: =B5+1 -> 3 | C6: =C5+365 -> 43555 | D6: 86068.5 | E6: =D6/D5-1 -> 0.078425599 | G6: =G5+1 -> 3 | H6: =H5+365 -> 43555 | I6: 74375.2 | J6: =I6/I5-1 -> 0.056023399 | L6: =L5+1 -> 3 | M6: =M5+365 -> 43555 | N6: 2261.0162 | O6: =N6/N5-1 -> 0.066641994
B7: =B6+1 -> 4 | C7: =C6+365 -> 43920 | D7: 75660 | E7: =D7/D6-1 -> -0.12093275 | G7: =G6+1 -> 4 | H7: =H6+365 -> 43920 | I7: 64312.6 | J7: =I7/I6-1 -> -0.1352951 | L7: =L6+1 -> 4 | M7: =M6+365 -> 43920 | N7: 1960.4369 | O7: =N7/N6-1 -> -0.1329399
B8: =B7+1 -> 5 | C8: =C7+365 -> 44285 | D8: 70372 | E8: =D8/D7-1 -> -0.06989162 | G8: =G7+1 -> 5 | H8: =H7+365 -> 44285 | I8: 60349.6 | J8: =I8/I7-1 -> -0.061620895 | L8: =L7+1 -> 5 | M8: =M7+365 -> 44285 | N8: 1863.0189 | O8: =N8/N7-1 -> -0.049692021
B9: =B8+1 -> 6 | C9: =C8+365 -> 44650 | D9: 88329.8 | E9: =D9/D8-1 -> 0.25518388 | G9: =G8+1 -> 6 | H9: =H8+365 -> 44650 | I9: 76699.9 | J9: =I9/I8-1 -> 0.2709264 | L9: =L8+1 -> 6 | M9: =M8+365 -> 44650 | N9: 2415.3128 | O9: =N9/N8-1 -> 0.29645107
B10: =B9+1 -> 7 | C10: =C9+365 -> 45015 | D10: 117571.3 | E10: =D10/D9-1 -> 0.33104909 | G10: =G9+1 -> 7 | H10: =H9+365 -> 45015 | I10: 103035.3 | J10: =I10/I9-1 -> 0.34335638 | L10: =L9+1 -> 7 | M10: =M9+365 -> 45015 | N10: 3240.9964 | O10: =N10/N9-1 -> 0.34185367
B11: =B10+1 -> 8 | C11: =C10+365 -> 45380 | D11: 141858.2 | E11: =D11/D10-1 -> 0.20657167 | G11: =G10+1 -> 8 | H11: =H10+365 -> 45380 | I11: 125608.1 | J11: =I11/I10-1 -> 0.21907832 | L11: =L10+1 -> 8 | M11: =M10+365 -> 45380 | N11: 3696.6412 | O11: =N11/N10-1 -> 0.1405879
B12: =B11+1 -> 9 | C12: =C11+365 -> 45745 | D12: 152913 | E12: =D12/D11-1 -> 0.077928523 | G12: =G11+1 -> 9 | H12: =H11+365 -> 45745 | I12: 136734.8 | J12: =I12/I11-1 -> 0.088582663 | L12: =L11+1 -> 9 | M12: =M11+365 -> 45745 | N12: 4001.673 | O12: =N12/N11-1 -> 0.082515935
B13: =B12+1 -> 10 | C13: =C12+365 -> 46110 | D13: 183316 | E13: =D13/D12-1 -> 0.19882548 | G13: =G12+1 -> 10 | H13: =H12+365 -> 46110 | I13: 163081.4 | J13: =I13/I12-1 -> 0.19268394 | L13: =L12+1 -> 10 | M13: =M12+365 -> 46110 | N13: 4823.855 | O13: =N13/N12-1 -> 0.20545955
B14: =B13+1 -> 11 | C14: =C13+365 -> 46475 | D14: =FORECAST(B14,$D$4:$D$13,$B$4:$B$13) -> 172113.13 | E14: =D14/D13-1 -> -0.061112323 | G14: =G13+1 -> 11 | H14: =H13+365 -> 46475 | I14: =FORECAST(G14,$I$4:$I$13,$G$4:$G$13) -> 152833.05 | J14: =I14/I13-1 -> -0.06284191 | L14: =L13+1 -> 11 | M14: =M13+365 -> 46475 | N14: =FORECAST(L14,$N$4:$N$13,$L$4:$L$13) -> 4548.8271 | O14: =N14/N13-1 -> -0.05701413
B15: =B14+1 -> 12 | C15: =C14+365 -> 46840 | D15: =FORECAST(B15,$D$4:$D$13,$B$4:$B$13) -> 184061.28 | E15: =D15/D14-1 -> 0.069420315 | G15: =G14+1 -> 12 | H15: =H14+365 -> 46840 | I15: =FORECAST(G15,$I$4:$I$13,$G$4:$G$13) -> 163629.37 | J15: =I15/I14-1 -> 0.070641244 | L15: =L14+1 -> 12 | M15: =M14+365 -> 46840 | N15: =FORECAST(L15,$N$4:$N$13,$L$4:$L$13) -> 4863.3418 | O15: =N15/N14-1 -> 0.06914195
B16: =B15+1 -> 13 | C16: =C15+365 -> 47205 | D16: =FORECAST(B16,$D$4:$D$13,$B$4:$B$13) -> 196009.43 | E16: =D16/D15-1 -> 0.064913967 | G16: =G15+1 -> 13 | H16: =H15+365 -> 47205 | I16: =FORECAST(G16,$I$4:$I$13,$G$4:$G$13) -> 174425.69 | J16: =I16/I15-1 -> 0.065980312 | L16: =L15+1 -> 13 | M16: =M15+365 -> 47205 | N16: =FORECAST(L16,$N$4:$N$13,$L$4:$L$13) -> 5177.8566 | O16: =N16/N15-1 -> 0.064670506
B17: =B16+1 -> 14 | C17: =C16+365 -> 47570 | D17: =FORECAST(B17,$D$4:$D$13,$B$4:$B$13) -> 207957.58 | E17: =D17/D16-1 -> 0.060957006 | G17: =G16+1 -> 14 | H17: =H16+365 -> 47570 | I17: =FORECAST(G17,$I$4:$I$13,$G$4:$G$13) -> 185222 | J17: =I17/I16-1 -> 0.061896371 | L17: =L16+1 -> 14 | M17: =M16+365 -> 47570 | N17: =FORECAST(L17,$N$4:$N$13,$L$4:$L$13) -> 5492.3714 | O17: =N17/N16-1 -> 0.060742272
B18: =B17+1 -> 15 | C18: =C17+365 -> 47935 | D18: =FORECAST(B18,$D$4:$D$13,$B$4:$B$13) -> 219905.72 | E18: =D18/D17-1 -> 0.057454737 | G18: =G17+1 -> 15 | H18: =H17+365 -> 47935 | I18: =FORECAST(G18,$I$4:$I$13,$G$4:$G$13) -> 196018.32 | J18: =I18/I17-1 -> 0.058288523 | L18: =L17+1 -> 15 | M18: =M17+365 -> 47935 | N18: =FORECAST(L18,$N$4:$N$13,$L$4:$L$13) -> 5806.8862 | O18: =N18/N17-1 -> 0.057263931

Sheet Data>

Sheet Data Sheet
A1: COMPANY NAME | B1: MARUTI SUZUKI INDIA LTD | E1: =IF(B2<>B3, "A NEW VERSION OF THE WORKSHEET IS AVAILABLE", "") -> A NEW VERSION OF THE WORKSHEET IS AVAILABLE
A2: LATEST VERSION | B2: ='Data Sheet'!B1&" -""" -> MARUTI SUZUKI INDIA LTD -" | E2: PLEASE DO NOT MAKE ANY CHANGES TO THIS SHEET
A3: CURRENT VERSION | B3: 2.1
A5: META
A6: Number of shares | B6: =IF(B9>0, B9/B8, 0) -> 31.440263
A7: Face Value | B7: 5
A8: Current Price | B8: 13444
A9: Market Capitalization | B9: 422682.9
A15: PROFIT & LOSS
A16: Report Date | B16: 42825 | C16: 43190 | D16: 43555 | E16: 43921 | F16: 44286 | G16: 44651 | H16: 45016 | I16: 45382 | J16: 45747 | K16: 46112
A17: Sales | B17: 68085 | C17: 79809.4 | D17: 86068.5 | E17: 75660 | F17: 70372 | G17: 88329.8 | H17: 117571.3 | I17: 141858.2 | J17: 152913 | K17: 183316
A18: Raw Material Cost | B18: 47121.5 | C18: 54945.3 | D18: 59346.6 | E18: 53402 | F18: 50550.5 | G18: 66137.1 | H18: 86654.7 | I18: 100119.5 | J18: 108718.3 | K18: 134848
A19: Change in Inventory | B19: 379.3 | C19: -40.8 | D19: -211.6 | E19: 238.7 | F19: -273.6 | G19: 93.1 | H19: 403.9 | I19: 378.6 | J19: 1227.5 | K19: 2272.5
A20: Power and Fuel | B20: 518.6 | C20: 673.4 | D20: 863.3 | E20: 699.5 | F20: 476.6 | G20: 630.9 | H20: 790 | I20: 1033.4 | J20: 1052.6
A21: Other Mfr. Exp | B21: 382.9 | C21: 462.1 | D21: 475.7 | E21: 378.1 | F21: 683.3 | G21: 852.5 | H21: 1120.7 | I21: 939.3 | J21: 1994.4
A22: Employee Cost | B22: 2360.3 | C22: 2863.4 | D22: 3285 | E22: 3416.2 | F22: 3431.6 | G22: 4051.4 | H22: 4634.6 | I22: 6301.6 | J22: 7026 | K22: 9049.7
A23: Selling and admin | B23: 6111.3 | C23: 6755.3 | D23: 8390.3 | E23: 8456.3 | F23: 7924 | G23: 9119.1 | H23: 11695 | I23: 12082.6 | J23: 11523.3
A24: Other Expenses | B24: 1548.4 | C24: 1951.2 | D24: 2439.7 | E24: 2191.6 | F24: 1621.8 | G24: 1879.9 | H24: 2051 | I24: 3134.1 | J24: 3602.3 | K24: 20234.6
A25: Other Income | B25: 2399.2 | C25: 2154.6 | D25: 2664.2 | E25: 3410.4 | F25: 3046.3 | G25: 1860.8 | H25: 2306.6 | I25: 4247.6 | J25: 5198.8 | K25: 4642.7
A26: Depreciation | B26: 2603.9 | C26: 2759.8 | D26: 3020.8 | E26: 3528.4 | F26: 3034.1 | G26: 2789 | H26: 2825.7 | I26: 5255.8 | J26: 5608.2 | K26: 6741.7
A27: Interest | B27: 89.4 | C27: 345.8 | D27: 75.9 | E27: 134.2 | F27: 101.8 | G27: 126.6 | H27: 187 | I27: 193.6 | J27: 194.2 | K27: 238.7
A28: Profit before tax | B28: 10127.2 | C28: 11166.9 | D28: 10623.8 | E28: 7102.8 | F28: 5321 | G28: 4697.2 | H28: 10323.1 | I28: 17424.5 | J28: 19620 | K28: 19118.5
A29: Tax | B29: 2616.2 | C29: 3286.2 | D29: 2973.2 | E29: 1425.2 | F29: 931.9 | G29: 817.7 | H29: 2112.1 | I29: 3936.3 | J29: 5119.8 | K29: 4439
A30: Net profit | B30: 7509.9 | C30: 7880 | D30: 7649.1 | E30: 5676 | F30: 4389.1 | G30: 3879.5 | H30: 8211 | I30: 13488.2 | J30: 14500.2 | K30: 14679.5
A31: Dividend Amount | B31: 2265 | C31: 2416 | D31: 2416 | E31: 1812 | F31: 1359 | G31: 1812 | H31: 2718 | I31: 3930 | J31: 4244.4 | K31: 4401.6
A40: Quarters
A41: Report Date | B41: 45291 | C41: 45382 | D41: 45473 | E41: 45565 | F41: 45657 | G41: 45747 | H41: 45838 | I41: 45930 | J41: 46022 | K41: 46112
A42: Sales | B42: 33512.8 | C42: 38471.2 | D42: 35779.4 | E42: 37449.2 | F42: 38764.3 | G42: 40920.1 | H42: 38605.2 | I42: 42344.2 | J42: 49904.1 | K42: 52462.5
A43: Expenses | B43: 29072.8 | C43: 33250.1 | D43: 30672.8 | E43: 32450.4 | F43: 33687.8 | G43: 36076.1 | H43: 33982.6 | I43: 37258.2 | J43: 44331 | K43: 46304.2
A44: Other Income | B44: 1052.9 | C44: 1261 | D44: 1118.1 | E44: 1570.5 | F44: 1124.8 | G44: 1583.1 | H44: 1923.7 | I44: 1013.5 | J44: 1140.5 | K44: 581.2
A45: Depreciation | B45: 1301.5 | C45: 1298.3 | D45: 1331.7 | E45: 1385.7 | F45: 1429 | G45: 1461.8 | H45: 1556 | I45: 1703 | J45: 1734.6 | K45: 1748.1
A46: Interest | B46: 35.8 | C46: 76.2 | D46: 57.3 | E46: 43 | F46: 46.3 | G46: 47.6 | H46: 46.8 | I46: 57.2 | J46: 61.7 | K46: 73
A47: Profit before tax | B47: 4155.6 | C47: 5107.6 | D47: 4835.7 | E47: 5140.6 | F47: 4726 | G47: 4917.7 | H47: 4943.5 | I47: 4339.3 | J47: 4917.3 | K47: 4918.4
A48: Tax | B48: 948.8 | C48: 1155.3 | D48: 1076 | E48: 2038.1 | F48: 999.1 | G48: 1006.6 | H48: 1151.1 | I48: 990.3 | J48: 1038.2 | K48: 1259.4
A49: Net profit | B49: 3206.8 | C49: 3952.3 | D49: 3759.7 | E49: 3102.5 | F49: 3726.9 | G49: 3911.1 | H49: 3792.4 | I49: 3349 | J49: 3879.1 | K49: 3659
A50: Operating Profit | B50: 4440 | C50: 5221.1 | D50: 5106.6 | E50: 4998.8 | F50: 5076.5 | G50: 4844 | H50: 4622.6 | I50: 5086 | J50: 5573.1 | K50: 6158.3
A55: BALANCE SHEET
A56: Report Date | B56: 42825 | C56: 43190 | D56: 43555 | E56: 43921 | F56: 44286 | G56: 44651 | H56: 45016 | I56: 45382 | J56: 45747 | K56: 46112
A57: Equity Share Capital | B57: 151 | C57: 151 | D57: 151 | E57: 151 | F57: 151 | G57: 151 | H57: 151 | I57: 157.2 | J57: 157.2 | K57: 157.2
A58: Reserves | B58: 36924.1 | C58: 42408.4 | D58: 46941.1 | E58: 49262 | F58: 52349.6 | G58: 55182.5 | H58: 61640.3 | I58: 85478.8 | J58: 96082.7 | K58: 106999.1
A59: Borrowings | B59: 483.6 | C59: 120.8 | D59: 159.6 | E59: 184.1 | F59: 540.9 | G59: 425.5 | H59: 1247.3 | I59: 118.6 | J59: 87 | K59: 102.5
A60: Other Liabilities | B60: 14401.8 | C60: 17568.2 | D60: 16717 | E60: 14030.6 | F60: 18334.6 | G60: 18896.5 | H60: 21558.3 | I60: 29549.5 | J60: 35644.3 | K60: 41622.2
A61: Total | B61: 51960.5 | C61: 60248.4 | D61: 63968.7 | E61: 63627.7 | F61: 71376.1 | G61: 74655.5 | H61: 84596.9 | I61: 115304.1 | J61: 131971.2 | K61: 148881
A62: Net Block | B62: 13310.7 | C62: 13388.8 | D62: 15437.3 | E62: 15744.4 | F62: 14988.7 | G62: 13747.2 | H62: 17830.4 | I62: 27864.8 | J62: 32982.7 | K62: 34955.4
A63: Capital Work in Progress | B63: 1252.3 | C63: 2132.1 | D63: 1606.9 | E63: 1415.2 | F63: 1496.8 | G63: 2936.5 | H63: 2904.1 | I63: 7734.8 | J63: 7929 | K63: 9406.2
A64: Investments | B64: 29150.6 | C64: 36123.1 | D64: 37503.6 | E64: 37488 | F64: 42944.8 | G64: 42034.7 | H64: 49184.3 | I64: 57296 | J64: 66265.4 | K64: 76838.5
A65: Other Assets | B65: 8246.9 | C65: 8604.4 | D65: 9420.9 | E65: 8980.1 | F65: 11945.8 | G65: 15937.1 | H65: 14678.1 | I65: 22408.5 | J65: 24794.1 | K65: 27680.9
A66: Total | B66: 51960.5 | C66: 60248.4 | D66: 63968.7 | E66: 63627.7 | F66: 71376.1 | G66: 74655.5 | H66: 84596.9 | I66: 115304.1 | J66: 131971.2 | K66: 148881
A67: Receivables | B67: 1202.6 | C67: 1465.4 | D67: 2312.8 | E67: 1977.7 | F67: 1279.9 | G67: 2034.5 | H67: 3301.4 | I67: 4596.8 | J67: 6539.7 | K67: 5342
... A69: Cash & Bank | B69: 23.5 | C69: 74 | D69: 187.8 | E69: 29 | F69: 3047.1 | G69: 3042.2 | H69: 41.6 | I69: 2827.4 | J69: 552.9 | K69: 1580
A70: No. of Equity Shares | B70: 302080060 | C70: 302080060 | D70: 302080060 | E70: 302080060 | F70: 302080060 | G70: 302080060 | H70: 302080060 | I70: 314402574 | J70: 314402574
A71: New Bonus Shares
A72: Face value | B72: 5 | C72: 5 | D72: 5 | E72: 5 | F72: 5 | G72: 5 | H72: 5 | I72: 5 | J72: 5 | K72: 5
A80: CASH FLOW:
A81: Report Date | B81: 42825 | C81: 43190 | D81: 43555 | E81: 43921 | F81: 44286 | G81: 44651 | H81: 45016 | I81: 45382 | J81: 45747 | K81: 46112
A82: Cash from Operating Activity | B82: 10282 | C82: 11787.9 | D82: 6600.9 | E82: 3495.8 | F82: 8856.2 | G82: 1840.5 | H82: 9251.4 | I82: 16801.1 | J82: 16136.2 | K82: 19099.9
A83: Cash from Investing Activity | B83: -9173.2 | C83: -8301.7 | D83: -3539.9 | E83: -556.6 | F83: -7291.3 | G83: -239.2 | H83: -8036.1 | I83: -11864.8 | J83: -14456.1 | K83: -14733.5
A84: Cash from Financing Activity | B84: -1129.3 | C84: -3436.1 | D84: -2947.9 | E84: -3104.3 | F84: -1544.9 | G84: -1607 | H84: -1213.1 | I84: -4062 | J84: -4155.1 | K84: -4484
A85: Net Cash Flow | B85: -20.5 | C85: 50.1 | D85: 113.1 | E85: -165.1 | F85: 20 | G85: -5.7 | H85: 2.2 | I85: 874.3 | J85: -2475 | K85: -117.6
A90: PRICE: | B90: 6015.7 | C90: 8861.1 | D90: 6672.55 | E90: 4288.3 | F90: 6859.2 | G90: 7561.3 | H90: 8292.15 | I90: 12600.35 | J90: 11522.15 | K90: 12306
A92: DERIVED:
A93: Adjusted Equity Shares in Cr | B93: 30.21 | C93: 30.21 | D93: 30.21 | E93: 30.21 | F93: 30.21 | G93: 30.21 | H93: 30.21 | I93: 31.44 | J93: 31.44 | K93: 31.44

Sheet Cash Flow
A2: # | B2: Cash Flow Statements
C3: 42064 | D3: 42430 | E3: 42795 | F3: 43160 | G3: 43525 | H3: 43891 | I3: 44256 | J3: 44621 | K3: 44986 | L3: 45352 | M3: 45717 | N3: 46082
B4: Cash from Operating Activity - | C4: 6449 | D4: 8482 | E4: 10282 | F4: 11788 | G4: 6601 | H4: 3496 | I4: 8856 | J4: 1840 | K4: 9251 | L4: 16801 | M4: 16136 | N4: 19100
B5: Profit from operations | C5: 6779 | D5: 8935 | E5: 10413 | F5: 12036 | G5: 11060 | H5: 7503 | I5: 5531 | J5: 5832 | K5: 11112 | L5: 18676 | M5: 20322 | N5: 21802
B6: Receivables | C6: 345 | D6: -204 | E6: 122 | F6: -262 | G6: -851 | H6: 340 | I6: 696 | J6: -764 | K6: -1258 | L6: -1316 | M6: -1969 | N6: 1236
B7: Inventory | C7: -982 | D7: -450 | E7: -131 | F7: 104 | G7: -162 | H7: 109 | I7: 165 | J7: -483 | K7: -751 | L7: 125 | M7: -1595 | N7: -4407
B8: Payables | C8: 712 | D8: 1789 | E8: 979 | F8: 2128 | G8: -858 | H8: -2155 | I8: 2680 | J8: -396 | K8: 2008 | L8: 3321 | M8: 3509 | N8: 5194
B9: Loans Advances | C9: 23 | D9: -1 | E9: 1 | F9: 0 | G9: -13 | H9: -1 | I9: -6 | J9: -8 | K9: 1 | L9: -3 | M9: -10 | N9: -1
B10: Other WC items | C10: 648 | D10: 325 | E10: 1222 | F10: 839 | G10: 569 | H10: -863 | I10: 801 | J10: -1162 | K10: 374 | L10: -406 | M10: -313 | N10: -387
B11: Working capital changes | C11: 745 | D11: 1460 | E11: 2192 | F11: 2808 | G11: -1315 | H11: -2570 | I11: 4336 | J11: -2813 | K11: 373 | L11: 1722 | M11: -378 | N11: 1635
B12: Direct taxes | C12: -1075 | D12: -1912 | E12: -2323 | F12: -3056 | G12: -3144 | H12: -1438 | I12: -1011 | J12: -1178 | K12: -2233 | L12: -3597 | M12: -3807 | N12: -4337
B13: Cash from Investing Activity - | C13: -4491 | D13: -7230 | E13: -9173 | F13: -8302 | G13: -3540 | H13: -557 | I13: -7291 | J13: -239 | K13: -8036 | L13: -11865 | M13: -14456 | N13: -14734
B14: Fixed assets purchased | C14: -3058 | D14: -2469 | E14: -3391 | F14: -3912 | G14: -4872 | H14: -3437 | I14: -2370 | J14: -3459 | K14: -6347 | L14: -9200 | M14: -10641 | N14: -10398
B15: Fixed assets sold | C15: 16 | D15: 12 | E15: 16 | F15: 26 | G15: 170 | H15: 37 | I15: 42 | J15: 136 | K15: 100 | L15: 45 | M15: 38 | N15: 52
... B30: Net Cash Flow | C30: -45 | D30: 16 | E30: -20 | F30: 50 | G30: 113 | H30: -165 | I30: 20 | J30: -6 | K30: 2 | L30: 874 | M30: -2475 | N30: -118
